[{"id": 6547760, "name": "Bastorf", "country": "DE", "coord": {"lon": 11.7, "lat": 54.133301}}, {"id": 2952235, "name": "Bastorf", "country": "DE", "coord": {"lon": 11.7, "lat": 54.133331}}, {"id": 2855514, "name": "Papenhagen", "country": "DE", "coord": {"lon": 12.87795, "lat": 54.202419}}, {"id": 6548364, "name": "Kobrow", "country": "DE", "coord": {"lon": 11.8, "lat": 53.6833}}, {"id": 2886934, "name": "Kobrow", "country": "DE", "coord": {"lon": 11.8, "lat": 53.683331}}, {"id": 2824927, "name": "S\u00fckow", "country": "DE", "coord": {"lon": 11.79828, "lat": 53.080921}}, {"id": 6548193, "name": "K\u00f6chelstorf", "country": "DE", "coord": {"lon": 11.1, "lat": 53.766701}}, {"id": 2886918, "name": "Kochelstorf", "country": "DE", "coord": {"lon": 11.1, "lat": 53.76667}}, {"id": 6548200, "name": "L\u00fctzow", "country": "DE", "coord": {"lon": 11.1833, "lat": 53.650002}}, {"id": 2874710, "name": "Lutzow", "country": "DE", "coord": {"lon": 11.18333, "lat": 53.650002}}, {"id": 6547408, "name": "B\u00fclow", "country": "DE", "coord": {"lon": 11.7667, "lat": 53.583302}}, {"id": 2941758, "name": "Bulow", "country": "DE", "coord": {"lon": 11.76667, "lat": 53.583328}}, {"id": 6551437, "name": "Grambek", "country": "DE", "coord": {"lon": 10.6833, "lat": 53.5667}}, {"id": 2918188, "name": "Grambek", "country": "DE", "coord": {"lon": 10.68081, "lat": 53.573872}}, {"id": 6551452, "name": "Hohenhorn", "country": "DE", "coord": {"lon": 10.3667, "lat": 53.483299}}, {"id": 2901691, "name": "Hohenhorn", "country": "DE", "coord": {"lon": 10.36667, "lat": 53.48333}}, {"id": 6552106, "name": "Itzstedt", "country": "DE", "coord": {"lon": 10.1559, "lat": 53.806198}}, {"id": 2895552, "name": "Itzstedt", "country": "DE", "coord": {"lon": 10.16667, "lat": 53.816669}}, {"id": 2825761, "name": "Strohbr\u00fcck", "country": "DE", "coord": {"lon": 9.98333, "lat": 54.333328}}, {"id": 6551719, "name": "Bothkamp", "country": "DE", "coord": {"lon": 10.1333, "lat": 54.200001}}, {"id": 2945797, "name": "Bothkamp", "country": "DE", "coord": {"lon": 10.13333, "lat": 54.200001}}, {"id": 6552184, "name": "Fitzbek", "country": "DE", "coord": {"lon": 9.76667, "lat": 54}}, {"id": 2926448, "name": "Fitzbek", "country": "DE", "coord": {"lon": 9.76667, "lat": 54}}, {"id": 6551564, "name": "Klixb\u00fcll", "country": "DE", "coord": {"lon": 8.9, "lat": 54.799999}}, {"id": 2887629, "name": "Klixbull", "country": "DE", "coord": {"lon": 8.9, "lat": 54.799999}}, {"id": 2931321, "name": "Ekeberg", "country": "DE", "coord": {"lon": 9.61667, "lat": 54.650002}}, {"id": 2917877, "name": "Gravelund", "country": "DE", "coord": {"lon": 9.3, "lat": 54.633331}}, {"id": 6551608, "name": "Stadum", "country": "DE", "coord": {"lon": 9.0527, "lat": 54.739101}}, {"id": 2829731, "name": "Stadum", "country": "DE", "coord": {"lon": 9.05, "lat": 54.73333}}, {"id": 6551535, "name": "Bosb\u00fcll", "country": "DE", "coord": {"lon": 8.86667, "lat": 54.8167}}, {"id": 2945942, "name": "Bosbull", "country": "DE", "coord": {"lon": 8.86667, "lat": 54.816669}}, {"id": 6552052, "name": "Sieverstedt", "country": "DE", "coord": {"lon": 9.48333, "lat": 54.650002}}, {"id": 2832276, "name": "Sieverstedt", "country": "DE", "coord": {"lon": 9.48333, "lat": 54.650002}}, {"id": 6556360, "name": "Eggst\u00e4tt", "country": "DE", "coord": {"lon": 12.3833, "lat": 47.9333}}, {"id": 2933018, "name": "Eggstatt", "country": "DE", "coord": {"lon": 12.37919, "lat": 47.926979}}, {"id": 2890861, "name": "Kindlbach", "country": "DE", "coord": {"lon": 13.15883, "lat": 48.423531}}, {"id": 2914426, "name": "Gr\u00fcnbichl", "country": "DE", "coord": {"lon": 13.26667, "lat": 48.916672}}, {"id": 2827968, "name": "Steinhof", "country": "DE", "coord": {"lon": 12.85, "lat": 49.099998}}, {"id": 2839192, "name": "Schiltern", "country": "DE", "coord": {"lon": 12.2, "lat": 49.549999}}, {"id": 2859122, "name": "Obersch\u00f6llenbach", "country": "DE", "coord": {"lon": 11.16735, "lat": 49.573269}}, {"id": 2916653, "name": "Gro\u00dfenbuch", "country": "DE", "coord": {"lon": 11.15988, "lat": 49.617661}}, {"id": 6556778, "name": "Weitramsdorf", "country": "DE", "coord": {"lon": 10.8833, "lat": 50.25}}, {"id": 2811611, "name": "Weitramsdorf", "country": "DE", "coord": {"lon": 10.88333, "lat": 50.25}}, {"id": 2891568, "name": "Kerkhofen", "country": "DE", "coord": {"lon": 11.39531, "lat": 49.171322}}, {"id": 6557127, "name": "Allmannshofen", "country": "DE", "coord": {"lon": 10.8, "lat": 48.616699}}, {"id": 2958309, "name": "Allmannshofen", "country": "DE", "coord": {"lon": 10.8, "lat": 48.616669}}, {"id": 6556085, "name": "Inzigkofen", "country": "DE", "coord": {"lon": 9.17964, "lat": 48.070419}}, {"id": 2895891, "name": "Inzigkofen", "country": "DE", "coord": {"lon": 9.17998, "lat": 48.070339}}, {"id": 2865460, "name": "Neuershausen", "country": "DE", "coord": {"lon": 7.76667, "lat": 48.066669}}, {"id": 2863136, "name": "Niedermanderscheid", "country": "DE", "coord": {"lon": 6.81667, "lat": 50.083328}}, {"id": 6554783, "name": "P\u00f6lich", "country": "DE", "coord": {"lon": 6.85, "lat": 49.799999}}, {"id": 2852882, "name": "Polich", "country": "DE", "coord": {"lon": 6.85, "lat": 49.799999}}, {"id": 6554736, "name": "Gusenburg", "country": "DE", "coord": {"lon": 6.9, "lat": 49.633301}}, {"id": 2913478, "name": "Gusenburg", "country": "DE", "coord": {"lon": 6.9, "lat": 49.633331}}, {"id": 6554364, "name": "Pantenburg", "country": "DE", "coord": {"lon": 6.83333, "lat": 50.083302}}, {"id": 2855563, "name": "Pantenburg", "country": "DE", "coord": {"lon": 6.83333, "lat": 50.083328}}, {"id": 6554649, "name": "Meisburg", "country": "DE", "coord": {"lon": 6.68333, "lat": 50.116699}}, {"id": 2872195, "name": "Meisburg", "country": "DE", "coord": {"lon": 6.68333, "lat": 50.116669}}, {"id": 2869194, "name": "Morsbacherhof", "country": "DE", "coord": {"lon": 7.81667, "lat": 49.700001}}, {"id": 2873864, "name": "Mannweiler", "country": "DE", "coord": {"lon": 7.8, "lat": 49.700001}}, {"id": 2889720, "name": "Klein-Bieberau", "country": "DE", "coord": {"lon": 8.76639, "lat": 49.758331}}, {"id": 2937650, "name": "Dickschied", "country": "DE", "coord": {"lon": 7.95, "lat": 50.116669}}, {"id": 2933209, "name": "Egenroth", "country": "DE", "coord": {"lon": 7.95, "lat": 50.183331}}, {"id": 6555265, "name": "Dolgesheim", "country": "DE", "coord": {"lon": 8.25694, "lat": 49.794399}}, {"id": 2936403, "name": "Dolgesheim", "country": "DE", "coord": {"lon": 8.25694, "lat": 49.794441}}, {"id": 6554852, "name": "Gau-Odernheim", "country": "DE", "coord": {"lon": 8.19417, "lat": 49.784698}}, {"id": 2922245, "name": "Gau-Odernheim", "country": "DE", "coord": {"lon": 8.19417, "lat": 49.784721}}, {"id": 6554829, "name": "Bechtolsheim", "country": "DE", "coord": {"lon": 8.19389, "lat": 49.804199}}, {"id": 2951736, "name": "Bechtolsheim", "country": "DE", "coord": {"lon": 8.19389, "lat": 49.804169}}, {"id": 2905305, "name": "Hessenthal", "country": "DE", "coord": {"lon": 9.28722, "lat": 49.92778}}, {"id": 2818916, "name": "Unterpreppach", "country": "DE", "coord": {"lon": 10.76667, "lat": 50.099998}}, {"id": 2924385, "name": "Friesenhausen", "country": "DE", "coord": {"lon": 10.48333, "lat": 50.166672}}, {"id": 6555680, "name": "Zuzenhausen", "country": "DE", "coord": {"lon": 8.8236, "lat": 49.295898}}, {"id": 2803642, "name": "Zuzenhausen", "country": "DE", "coord": {"lon": 8.82254, "lat": 49.29636}}, {"id": 2909347, "name": "Hassenhausen", "country": "DE", "coord": {"lon": 8.73333, "lat": 50.700001}}, {"id": 6554121, "name": "Caan", "country": "DE", "coord": {"lon": 7.61667, "lat": 50.466702}}, {"id": 3207692, "name": "Caan", "country": "DE", "coord": {"lon": 7.61667, "lat": 50.466671}}, {"id": 6554267, "name": "Seck", "country": "DE", "coord": {"lon": 8.05, "lat": 50.583302}}, {"id": 2834082, "name": "Seck", "country": "DE", "coord": {"lon": 8.05, "lat": 50.583328}}, {"id": 6554130, "name": "Freirachdorf", "country": "DE", "coord": {"lon": 7.71667, "lat": 50.583302}}, {"id": 2925051, "name": "Freirachdorf", "country": "DE", "coord": {"lon": 7.71667, "lat": 50.583328}}, {"id": 6553425, "name": "Niedersteinebach", "country": "DE", "coord": {"lon": 7.5, "lat": 50.599998}}, {"id": 2862833, "name": "Niedersteinebach", "country": "DE", "coord": {"lon": 7.50692, "lat": 50.600182}}, {"id": 6553858, "name": "Stebach", "country": "DE", "coord": {"lon": 7.65, "lat": 50.516701}}, {"id": 2829280, "name": "Stebach", "country": "DE", "coord": {"lon": 7.65, "lat": 50.51667}}, {"id": 2839186, "name": "Schimborn", "country": "DE", "coord": {"lon": 9.18333, "lat": 50.049999}}, {"id": 2957637, "name": "Altenha\u00dflau", "country": "DE", "coord": {"lon": 9.2, "lat": 50.183331}}, {"id": 2879143, "name": "Leippen", "country": "DE", "coord": {"lon": 13.33333, "lat": 51.133331}}, {"id": 2889754, "name": "Kleinbautzen", "country": "DE", "coord": {"lon": 14.53333, "lat": 51.216671}}, {"id": 2925264, "name": "Frauwalde", "country": "DE", "coord": {"lon": 13.71667, "lat": 51.383331}}, {"id": 2947521, "name": "Blumenthal", "country": "DE", "coord": {"lon": 14.4, "lat": 51.133331}}, {"id": 2871586, "name": "Methewitz", "country": "DE", "coord": {"lon": 12.28333, "lat": 51.116669}}, {"id": 6548624, "name": "Steinigtwolmsdorf", "country": "DE", "coord": {"lon": 14.35, "lat": 51.0667}}, {"id": 2827907, "name": "Steinigtwolmsdorf", "country": "DE", "coord": {"lon": 14.3454, "lat": 51.063141}}, {"id": 2878908, "name": "Lenau", "country": "DE", "coord": {"lon": 11.89304, "lat": 49.91608}}, {"id": 2957436, "name": "Altentreswitz", "country": "DE", "coord": {"lon": 12.36667, "lat": 49.583328}}, {"id": 2834141, "name": "Schwoitsch", "country": "DE", "coord": {"lon": 12.13333, "lat": 51.433331}}, {"id": 2804664, "name": "Zeuchfeld", "country": "DE", "coord": {"lon": 11.83333, "lat": 51.23333}}, {"id": 2951423, "name": "Beidersee", "country": "DE", "coord": {"lon": 11.9, "lat": 51.566669}}, {"id": 6559291, "name": "Gierst\u00e4dt", "country": "DE", "coord": {"lon": 10.86262, "lat": 51.036179}}, {"id": 2920581, "name": "Gierstadt", "country": "DE", "coord": {"lon": 10.83333, "lat": 51.049999}}, {"id": 6548636, "name": "H\u00e4hnichen", "country": "DE", "coord": {"lon": 14.8667, "lat": 51.366699}}, {"id": 2912184, "name": "Hahnichen", "country": "DE", "coord": {"lon": 14.86098, "lat": 51.365398}}, {"id": 2803524, "name": "Zwietow", "country": "DE", "coord": {"lon": 13.96667, "lat": 51.683331}}, {"id": 2876859, "name": "Lipten", "country": "DE", "coord": {"lon": 13.93333, "lat": 51.650002}}, {"id": 2945364, "name": "Brandenberg", "country": "DE", "coord": {"lon": 6.41667, "lat": 50.700001}}, {"id": 2854957, "name": "Penkun", "country": "DE", "coord": {"lon": 14.25, "lat": 53.299999}}, {"id": 6548099, "name": "Vipperow", "country": "DE", "coord": {"lon": 12.6833, "lat": 53.333302}}, {"id": 2817148, "name": "Vipperow", "country": "DE", "coord": {"lon": 12.68887, "lat": 53.326111}}, {"id": 2847612, "name": "Rheinsberg", "country": "DE", "coord": {"lon": 12.89885, "lat": 53.09972}}, {"id": 2848146, "name": "Rentrup", "country": "DE", "coord": {"lon": 7.46667, "lat": 52.533329}}, {"id": 2925208, "name": "Freetz", "country": "DE", "coord": {"lon": 9.53333, "lat": 53.316669}}, {"id": 2905635, "name": "Herrnried", "country": "DE", "coord": {"lon": 11.71872, "lat": 49.105339}}, {"id": 6552376, "name": "Velpke", "country": "DE", "coord": {"lon": 10.9333, "lat": 52.400002}}, {"id": 2817679, "name": "Velpke", "country": "DE", "coord": {"lon": 10.93637, "lat": 52.40797}}, {"id": 6555461, "name": "Hattenhofen", "country": "DE", "coord": {"lon": 9.57476, "lat": 48.666359}}, {"id": 2909252, "name": "Hattenhofen", "country": "DE", "coord": {"lon": 9.57456, "lat": 48.666481}}, {"id": 6557279, "name": "F\u00fcnfstetten", "country": "DE", "coord": {"lon": 10.7667, "lat": 48.8167}}, {"id": 2923753, "name": "Funfstetten", "country": "DE", "coord": {"lon": 10.76667, "lat": 48.816669}}, {"id": 2866056, "name": "Neuclausnitz", "country": "DE", "coord": {"lon": 13.53333, "lat": 50.73333}}, {"id": 6553975, "name": "Uhler", "country": "DE", "coord": {"lon": 7.43333, "lat": 50.083302}}, {"id": 2820338, "name": "Uhler", "country": "DE", "coord": {"lon": 7.43333, "lat": 50.083328}}, {"id": 2929375, "name": "Ermstedt", "country": "DE", "coord": {"lon": 10.88333, "lat": 50.966671}}, {"id": 2829513, "name": "Stapelburg", "country": "DE", "coord": {"lon": 10.66667, "lat": 51.900002}}, {"id": 2938942, "name": "Dardesheim", "country": "DE", "coord": {"lon": 10.83333, "lat": 51.966671}}, {"id": 2815328, "name": "Waibstadt", "country": "DE", "coord": {"lon": 8.91917, "lat": 49.298061}}, {"id": 6553486, "name": "Frei-Laubersheim", "country": "DE", "coord": {"lon": 7.9, "lat": 49.799999}}, {"id": 2925079, "name": "Frei-Laubersheim", "country": "DE", "coord": {"lon": 7.9, "lat": 49.799999}}, {"id": 2824601, "name": "Suppo", "country": "DE", "coord": {"lon": 14.46667, "lat": 51.099998}}, {"id": 2872536, "name": "Medewitz", "country": "DE", "coord": {"lon": 14.28333, "lat": 51.150002}}, {"id": 2855587, "name": "Pannewitz am Taucher", "country": "DE", "coord": {"lon": 14.25, "lat": 51.200001}}, {"id": 2893483, "name": "Kaltohmfeld", "country": "DE", "coord": {"lon": 10.39925, "lat": 51.456039}}, {"id": 2838240, "name": "Schlotheim", "country": "DE", "coord": {"lon": 10.66667, "lat": 51.25}}, {"id": 2827678, "name": "Steinsdorf", "country": "DE", "coord": {"lon": 11.49436, "lat": 50.584759}}, {"id": 2918770, "name": "Gossnitz", "country": "DE", "coord": {"lon": 12.43333, "lat": 50.900002}}, {"id": 2931242, "name": "Elbitz", "country": "DE", "coord": {"lon": 11.71667, "lat": 51.533329}}, {"id": 2898299, "name": "Hoym", "country": "DE", "coord": {"lon": 11.31244, "lat": 51.782921}}, {"id": 2947477, "name": "Bobbau", "country": "DE", "coord": {"lon": 12.26667, "lat": 51.683331}}, {"id": 2876714, "name": "Loberitz", "country": "DE", "coord": {"lon": 12.15, "lat": 51.650002}}, {"id": 2804303, "name": "Ziepel", "country": "DE", "coord": {"lon": 11.86667, "lat": 52.150002}}, {"id": 2930154, "name": "Engetried", "country": "DE", "coord": {"lon": 10.4, "lat": 47.933331}}, {"id": 2826902, "name": "St\u00f6ckach", "country": "DE", "coord": {"lon": 11.22494, "lat": 49.613602}}, {"id": 2880911, "name": "Langensohl", "country": "DE", "coord": {"lon": 7.75712, "lat": 49.369968}}, {"id": 6555038, "name": "Hochspeyer", "country": "DE", "coord": {"lon": 7.9, "lat": 49.450001}}, {"id": 2903026, "name": "Hochspeyer", "country": "DE", "coord": {"lon": 7.9, "lat": 49.450001}}, {"id": 2931226, "name": "Elchesheim", "country": "DE", "coord": {"lon": 8.21667, "lat": 48.933331}}, {"id": 6553447, "name": "S\u00f6rth", "country": "DE", "coord": {"lon": 7.68333, "lat": 50.700001}}, {"id": 2830920, "name": "Sorth", "country": "DE", "coord": {"lon": 7.68333, "lat": 50.700001}}, {"id": 2897294, "name": "Hunteburg", "country": "DE", "coord": {"lon": 8.28333, "lat": 52.433331}}, {"id": 2895525, "name": "Jabel", "country": "DE", "coord": {"lon": 12.44253, "lat": 53.16983}}, {"id": 2806251, "name": "W\u00f6lzow", "country": "DE", "coord": {"lon": 11.12044, "lat": 53.498932}}, {"id": 6548165, "name": "Bibow", "country": "DE", "coord": {"lon": 11.6333, "lat": 53.783298}}, {"id": 2949366, "name": "Bibow", "country": "DE", "coord": {"lon": 11.63333, "lat": 53.783329}}, {"id": 2922829, "name": "Gallentin", "country": "DE", "coord": {"lon": 11.44887, "lat": 53.758911}}, {"id": 2924313, "name": "Frohburg", "country": "DE", "coord": {"lon": 12.55, "lat": 51.049999}}, {"id": 2849763, "name": "Rebgeshain", "country": "DE", "coord": {"lon": 9.23333, "lat": 50.566669}}, {"id": 2822860, "name": "Thenn", "country": "DE", "coord": {"lon": 11.96667, "lat": 48.400002}}, {"id": 2822004, "name": "Todtenberg", "country": "DE", "coord": {"lon": 7.88333, "lat": 50.616669}}, {"id": 6553875, "name": "Benzweiler", "country": "DE", "coord": {"lon": 7.6, "lat": 50.016701}}, {"id": 2950901, "name": "Benzweiler", "country": "DE", "coord": {"lon": 7.6, "lat": 50.01667}}, {"id": 6555224, "name": "Venningen", "country": "DE", "coord": {"lon": 8.17361, "lat": 49.2817}}, {"id": 2817627, "name": "Venningen", "country": "DE", "coord": {"lon": 8.17361, "lat": 49.28167}}, {"id": 2837829, "name": "Schmidthahn", "country": "DE", "coord": {"lon": 7.81667, "lat": 50.599998}}, {"id": 2906102, "name": "Hergertswiesen", "country": "DE", "coord": {"lon": 11.11667, "lat": 48.333328}}, {"id": 2817581, "name": "Veringenstadt", "country": "DE", "coord": {"lon": 9.21079, "lat": 48.18515}}, {"id": 6555149, "name": "Sch\u00f6nenberg-K\u00fcbelberg", "country": "DE", "coord": {"lon": 7.36667, "lat": 49.400002}}, {"id": 3207540, "name": "Schonenberg-Kubelberg", "country": "DE", "coord": {"lon": 7.36667, "lat": 49.400002}}, {"id": 2831760, "name": "Skassa", "country": "DE", "coord": {"lon": 13.46667, "lat": 51.283329}}, {"id": 2861430, "name": "Oberaltertheim", "country": "DE", "coord": {"lon": 9.76417, "lat": 49.727779}}, {"id": 6554120, "name": "Breitenau", "country": "DE", "coord": {"lon": 7.68333, "lat": 50.5}}, {"id": 2944730, "name": "Breitenau", "country": "DE", "coord": {"lon": 7.68333, "lat": 50.5}}, {"id": 2830017, "name": "Springiersbach", "country": "DE", "coord": {"lon": 7.06667, "lat": 50.033329}}, {"id": 6554786, "name": "Reinsfeld", "country": "DE", "coord": {"lon": 6.8849, "lat": 49.683601}}, {"id": 2848710, "name": "Reinsfeld", "country": "DE", "coord": {"lon": 6.88333, "lat": 49.683331}}, {"id": 2898694, "name": "H\u00f6rspe", "country": "DE", "coord": {"lon": 8.58333, "lat": 53.133331}}, {"id": 6551838, "name": "Friedrichsholm", "country": "DE", "coord": {"lon": 9.43333, "lat": 54.299999}}, {"id": 2924515, "name": "Friedrichsholm", "country": "DE", "coord": {"lon": 9.43333, "lat": 54.299999}}, {"id": 6551763, "name": "Prasdorf", "country": "DE", "coord": {"lon": 10.3, "lat": 54.383301}}, {"id": 2852326, "name": "Prasdorf", "country": "DE", "coord": {"lon": 10.3, "lat": 54.383331}}, {"id": 6549987, "name": "Topfstedt", "country": "DE", "coord": {"lon": 10.9667, "lat": 51.266701}}, {"id": 3207140, "name": "Topfstedt", "country": "DE", "coord": {"lon": 10.96667, "lat": 51.26667}}, {"id": 6554628, "name": "Deudesfeld", "country": "DE", "coord": {"lon": 6.73333, "lat": 50.099998}}, {"id": 2937868, "name": "Deudesfeld", "country": "DE", "coord": {"lon": 6.73333, "lat": 50.099998}}, {"id": 3209074, "name": "Neu Steddorf", "country": "DE", "coord": {"lon": 10.47941, "lat": 53.131989}}, {"id": 6554898, "name": "Esthal", "country": "DE", "coord": {"lon": 7.98333, "lat": 49.383301}}, {"id": 2928715, "name": "Esthal", "country": "DE", "coord": {"lon": 7.98333, "lat": 49.383331}}, {"id": 6551461, "name": "Klein Zecher", "country": "DE", "coord": {"lon": 10.8667, "lat": 53.583302}}, {"id": 2887952, "name": "Klein Zecher", "country": "DE", "coord": {"lon": 10.86667, "lat": 53.583328}}, {"id": 6556573, "name": "Aholfing", "country": "DE", "coord": {"lon": 12.4667, "lat": 48.950001}}, {"id": 2959143, "name": "Aholfing", "country": "DE", "coord": {"lon": 12.46667, "lat": 48.950001}}, {"id": 6554902, "name": "Gerolsheim", "country": "DE", "coord": {"lon": 8.26389, "lat": 49.547798}}, {"id": 2920964, "name": "Gerolsheim", "country": "DE", "coord": {"lon": 8.26389, "lat": 49.547779}}, {"id": 6549842, "name": "Ilfeld", "country": "DE", "coord": {"lon": 10.7833, "lat": 51.583302}}, {"id": 2850870, "name": "Rahm", "country": "DE", "coord": {"lon": 6.43333, "lat": 51.433331}}, {"id": 2906081, "name": "Heringnohe", "country": "DE", "coord": {"lon": 11.76667, "lat": 49.633331}}, {"id": 2909073, "name": "Haunkenzell", "country": "DE", "coord": {"lon": 12.63333, "lat": 49.033329}}, {"id": 2813650, "name": "Wattenbach", "country": "DE", "coord": {"lon": 10.7, "lat": 49.25}}, {"id": 2911285, "name": "Wandsbek", "country": "DE", "coord": {"lon": 10.1, "lat": 53.566669}}, {"id": 2846518, "name": "Rintheim", "country": "DE", "coord": {"lon": 8.4393, "lat": 49.01215}}, {"id": 2833013, "name": "Sennestadt", "country": "DE", "coord": {"lon": 8.61667, "lat": 51.950001}}, {"id": 2941252, "name": "B\u00fcrgh\u00f6fe", "country": "DE", "coord": {"lon": 9.93333, "lat": 48.23333}}, {"id": 2823413, "name": "Testorf", "country": "DE", "coord": {"lon": 10.71768, "lat": 53.046009}}, {"id": 2857613, "name": "Ohnhorst", "country": "DE", "coord": {"lon": 10.56524, "lat": 52.403782}}, {"id": 6552835, "name": "Suhlendorf", "country": "DE", "coord": {"lon": 10.7667, "lat": 52.9333}}, {"id": 2824940, "name": "Suhlendorf", "country": "DE", "coord": {"lon": 10.76667, "lat": 52.933331}}, {"id": 6551973, "name": "Klein Rheide", "country": "DE", "coord": {"lon": 9.48333, "lat": 54.450001}}, {"id": 2888333, "name": "Klein Rheide", "country": "DE", "coord": {"lon": 9.48333, "lat": 54.450001}}, {"id": 6551969, "name": "J\u00fcbek", "country": "DE", "coord": {"lon": 9.4, "lat": 54.549999}}, {"id": 2894644, "name": "Jubek", "country": "DE", "coord": {"lon": 9.4, "lat": 54.549999}}, {"id": 6553867, "name": "Alterk\u00fclz", "country": "DE", "coord": {"lon": 7.46667, "lat": 50.033298}}, {"id": 2957351, "name": "Alterkulz", "country": "DE", "coord": {"lon": 7.46667, "lat": 50.033329}}, {"id": 6553913, "name": "Klosterkumbd", "country": "DE", "coord": {"lon": 7.53333, "lat": 50.033298}}, {"id": 2887453, "name": "Klosterkumbd", "country": "DE", "coord": {"lon": 7.53333, "lat": 50.033329}}, {"id": 2856158, "name": "\u00d6tjendorf", "country": "DE", "coord": {"lon": 10.33333, "lat": 53.683331}}, {"id": 6547588, "name": "Tr\u00f6bitz", "country": "DE", "coord": {"lon": 13.4333, "lat": 51.599998}}, {"id": 2821071, "name": "Trobitz", "country": "DE", "coord": {"lon": 13.43333, "lat": 51.599998}}, {"id": 2927560, "name": "Fehrenbach", "country": "DE", "coord": {"lon": 10.91667, "lat": 50.5}}, {"id": 6550166, "name": "Dingsleben", "country": "DE", "coord": {"lon": 10.6, "lat": 50.4333}}, {"id": 2936904, "name": "Dingsleben", "country": "DE", "coord": {"lon": 10.6, "lat": 50.433331}}, {"id": 2869169, "name": "M\u00f6rsdorf", "country": "DE", "coord": {"lon": 11.28333, "lat": 49.200001}}, {"id": 2815272, "name": "Waizenhofen", "country": "DE", "coord": {"lon": 11.23333, "lat": 49.066669}}, {"id": 6556903, "name": "Gerhardshofen", "country": "DE", "coord": {"lon": 10.7065, "lat": 49.619999}}, {"id": 2921119, "name": "Gerhardshofen", "country": "DE", "coord": {"lon": 10.69133, "lat": 49.631229}}, {"id": 2959532, "name": "Adelmannsdorf", "country": "DE", "coord": {"lon": 10.75, "lat": 49.216671}}, {"id": 2935257, "name": "Drehenthalerhof", "country": "DE", "coord": {"lon": 7.81667, "lat": 49.51667}}, {"id": 6555649, "name": "Neckargerach", "country": "DE", "coord": {"lon": 9.06667, "lat": 49.400002}}, {"id": 2866773, "name": "Neckargerach", "country": "DE", "coord": {"lon": 9.06667, "lat": 49.400002}}, {"id": 2804138, "name": "Zingsheim", "country": "DE", "coord": {"lon": 6.65, "lat": 50.51667}}, {"id": 2832066, "name": "Silmenitz", "country": "DE", "coord": {"lon": 13.38333, "lat": 54.283329}}, {"id": 3208739, "name": "Damelang-Freienthal", "country": "DE", "coord": {"lon": 12.7, "lat": 52.23333}}, {"id": 6547687, "name": "Wusterwitz", "country": "DE", "coord": {"lon": 12.4, "lat": 52.383301}}, {"id": 2805475, "name": "Wusterwitz", "country": "DE", "coord": {"lon": 12.4, "lat": 52.383331}}, {"id": 6551926, "name": "Tappendorf", "country": "DE", "coord": {"lon": 9.68333, "lat": 54.099998}}, {"id": 2823997, "name": "Tappendorf", "country": "DE", "coord": {"lon": 9.68333, "lat": 54.099998}}, {"id": 6551723, "name": "Dobersdorf", "country": "DE", "coord": {"lon": 10.2833, "lat": 54.3167}}, {"id": 2936613, "name": "Dobersdorf", "country": "DE", "coord": {"lon": 10.28011, "lat": 54.318932}}, {"id": 6551545, "name": "Fresendelf", "country": "DE", "coord": {"lon": 9.25, "lat": 54.400002}}, {"id": 2924956, "name": "Fresendelf", "country": "DE", "coord": {"lon": 9.24688, "lat": 54.393749}}, {"id": 2930810, "name": "Elpersb\u00fcttelerdonn", "country": "DE", "coord": {"lon": 9.06667, "lat": 54.066669}}, {"id": 2888784, "name": "Klein Havighorst", "country": "DE", "coord": {"lon": 10.16667, "lat": 54.23333}}, {"id": 2867749, "name": "Mulsum", "country": "DE", "coord": {"lon": 9.3, "lat": 53.51667}}, {"id": 6551359, "name": "Nordhastedt", "country": "DE", "coord": {"lon": 9.18333, "lat": 54.166698}}, {"id": 2861988, "name": "Nordhastedt", "country": "DE", "coord": {"lon": 9.18333, "lat": 54.166672}}, {"id": 6551333, "name": "Hemmingstedt", "country": "DE", "coord": {"lon": 9.06667, "lat": 54.150002}}, {"id": 2906527, "name": "Hemmingstedt", "country": "DE", "coord": {"lon": 9.06667, "lat": 54.150002}}, {"id": 2897021, "name": "H\u00fctten", "country": "DE", "coord": {"lon": 9.6, "lat": 54.133331}}, {"id": 6551803, "name": "Beringstedt", "country": "DE", "coord": {"lon": 9.53333, "lat": 54.116699}}, {"id": 2950214, "name": "Beringstedt", "country": "DE", "coord": {"lon": 9.53333, "lat": 54.116669}}, {"id": 2956973, "name": "Alt M\u00fchlendorf", "country": "DE", "coord": {"lon": 9.86667, "lat": 54.216671}}, {"id": 2823546, "name": "Tempelberg", "country": "DE", "coord": {"lon": 14.16667, "lat": 52.450001}}, {"id": 6554209, "name": "Girkenroth", "country": "DE", "coord": {"lon": 7.96667, "lat": 50.516701}}, {"id": 2920299, "name": "Girkenroth", "country": "DE", "coord": {"lon": 7.96667, "lat": 50.51667}}, {"id": 2857682, "name": "Ohlenberg", "country": "DE", "coord": {"lon": 7.28207, "lat": 50.588249}}, {"id": 6555191, "name": "Herxheimweyher", "country": "DE", "coord": {"lon": 8.255, "lat": 49.1525}}, {"id": 2905526, "name": "Herxheimweyher", "country": "DE", "coord": {"lon": 8.255, "lat": 49.1525}}, {"id": 2929826, "name": "Eppishofen", "country": "DE", "coord": {"lon": 10.60095, "lat": 48.460739}}, {"id": 2925121, "name": "Freihalden", "country": "DE", "coord": {"lon": 10.49452, "lat": 48.3867}}, {"id": 2955581, "name": "Arlaching", "country": "DE", "coord": {"lon": 12.49686, "lat": 47.92284}}, {"id": 2894760, "name": "Johannisthal", "country": "DE", "coord": {"lon": 11.16667, "lat": 49.549999}}, {"id": 6555622, "name": "Au am Rhein", "country": "DE", "coord": {"lon": 8.2464, "lat": 48.9454}}, {"id": 2954775, "name": "Au am Rhein", "country": "DE", "coord": {"lon": 8.23333, "lat": 48.950001}}, {"id": 2809886, "name": "Wetzldorf", "country": "DE", "coord": {"lon": 12.06667, "lat": 49.866669}}, {"id": 2803577, "name": "Zwergau", "country": "DE", "coord": {"lon": 11.96667, "lat": 49.866669}}, {"id": 6554813, "name": "Welschbillig", "country": "DE", "coord": {"lon": 6.565, "lat": 49.8601}}, {"id": 2811420, "name": "Welschbillig", "country": "DE", "coord": {"lon": 6.56667, "lat": 49.849998}}, {"id": 6554293, "name": "Arenrath", "country": "DE", "coord": {"lon": 6.73333, "lat": 49.950001}}, {"id": 2955645, "name": "Arenrath", "country": "DE", "coord": {"lon": 6.73333, "lat": 49.950001}}, {"id": 6554803, "name": "Waldrach", "country": "DE", "coord": {"lon": 6.75, "lat": 49.75}}, {"id": 2814832, "name": "Waldrach", "country": "DE", "coord": {"lon": 6.74543, "lat": 49.746231}}, {"id": 2854604, "name": "Petersw\u00f6rth", "country": "DE", "coord": {"lon": 10.37298, "lat": 48.526718}}, {"id": 2956837, "name": "Altstadt", "country": "DE", "coord": {"lon": 7.81667, "lat": 50.666672}}, {"id": 6553500, "name": "H\u00fcffelsheim", "country": "DE", "coord": {"lon": 7.8, "lat": 49.8167}}, {"id": 2898036, "name": "Huffelsheim", "country": "DE", "coord": {"lon": 7.8, "lat": 49.816669}}, {"id": 2865656, "name": "Neuenhuntorf", "country": "DE", "coord": {"lon": 8.43333, "lat": 53.183331}}, {"id": 2918217, "name": "Grafwegen", "country": "DE", "coord": {"lon": 5.95, "lat": 51.75}}, {"id": 2947180, "name": "Boddinsfelde", "country": "DE", "coord": {"lon": 13.5, "lat": 52.299999}}, {"id": 2924407, "name": "Frienstedt", "country": "DE", "coord": {"lon": 10.90625, "lat": 50.952751}}, {"id": 6554166, "name": "Oberhaid", "country": "DE", "coord": {"lon": 7.71667, "lat": 50.516701}}, {"id": 2860509, "name": "Oberhaid", "country": "DE", "coord": {"lon": 7.71667, "lat": 50.51667}}, {"id": 2811022, "name": "Wenze", "country": "DE", "coord": {"lon": 11.11667, "lat": 52.566669}}, {"id": 2895046, "name": "Jemmeritz", "country": "DE", "coord": {"lon": 11.25, "lat": 52.633331}}, {"id": 2819390, "name": "Unterhegenau", "country": "DE", "coord": {"lon": 10.4, "lat": 49.383331}}, {"id": 2931262, "name": "Elbersreuth", "country": "DE", "coord": {"lon": 11.56667, "lat": 50.25}}, {"id": 6555000, "name": "Seelen", "country": "DE", "coord": {"lon": 7.71667, "lat": 49.599998}}, {"id": 2833683, "name": "Seelen", "country": "DE", "coord": {"lon": 7.71667, "lat": 49.599998}}, {"id": 6553413, "name": "Kraam", "country": "DE", "coord": {"lon": 7.53333, "lat": 50.700001}}, {"id": 2885050, "name": "Kraam", "country": "DE", "coord": {"lon": 7.53333, "lat": 50.700001}}, {"id": 6553725, "name": "Senheim", "country": "DE", "coord": {"lon": 7.20833, "lat": 50.083302}}, {"id": 2833034, "name": "Senheim", "country": "DE", "coord": {"lon": 7.21667, "lat": 50.083328}}, {"id": 2934184, "name": "Duttweiler", "country": "DE", "coord": {"lon": 8.21389, "lat": 49.299171}}, {"id": 6549996, "name": "Bauerbach", "country": "DE", "coord": {"lon": 10.4, "lat": 50.5}}, {"id": 2952161, "name": "Bauerbach", "country": "DE", "coord": {"lon": 10.4, "lat": 50.5}}, {"id": 2951454, "name": "Behringen", "country": "DE", "coord": {"lon": 11.01667, "lat": 50.783329}}, {"id": 2939694, "name": "Cumbach", "country": "DE", "coord": {"lon": 10.61667, "lat": 50.883331}}, {"id": 6556828, "name": "Tr\u00f6stau", "country": "DE", "coord": {"lon": 11.95, "lat": 50.016701}}, {"id": 2820967, "name": "Trostau", "country": "DE", "coord": {"lon": 11.95, "lat": 50.01667}}, {"id": 2951552, "name": "Beerhof", "country": "DE", "coord": {"lon": 11.85, "lat": 49.883331}}, {"id": 2917147, "name": "Gr\u00f6na", "country": "DE", "coord": {"lon": 11.7, "lat": 51.76667}}, {"id": 2869229, "name": "Morl", "country": "DE", "coord": {"lon": 11.91667, "lat": 51.549999}}, {"id": 2935528, "name": "D\u00f6rstewitz", "country": "DE", "coord": {"lon": 11.91667, "lat": 51.400002}}, {"id": 6548784, "name": "Cavertitz", "country": "DE", "coord": {"lon": 13.1333, "lat": 51.383301}}, {"id": 2940218, "name": "Cavertitz", "country": "DE", "coord": {"lon": 13.13333, "lat": 51.383331}}, {"id": 2872388, "name": "Mehren", "country": "DE", "coord": {"lon": 13.41667, "lat": 51.150002}}, {"id": 2824373, "name": "Taiding", "country": "DE", "coord": {"lon": 12.66252, "lat": 48.803299}}, {"id": 2924909, "name": "Freudeneck", "country": "DE", "coord": {"lon": 10.87955, "lat": 50.035309}}, {"id": 2947420, "name": "Bochow", "country": "DE", "coord": {"lon": 13.1, "lat": 51.950001}}, {"id": 2952184, "name": "Batzlow", "country": "DE", "coord": {"lon": 14.12009, "lat": 52.637798}}, {"id": 2957134, "name": "Althen", "country": "DE", "coord": {"lon": 12.52047, "lat": 51.340481}}, {"id": 6550157, "name": "Udestedt", "country": "DE", "coord": {"lon": 11.1333, "lat": 51.049999}}, {"id": 2820491, "name": "Udestedt", "country": "DE", "coord": {"lon": 11.13333, "lat": 51.049999}}, {"id": 2879745, "name": "Leckwitz", "country": "DE", "coord": {"lon": 13.4, "lat": 51.299999}}, {"id": 2936520, "name": "Dodendorf", "country": "DE", "coord": {"lon": 11.61564, "lat": 52.040668}}, {"id": 6553734, "name": "Weiler", "country": "DE", "coord": {"lon": 7.08333, "lat": 50.150002}}, {"id": 2812582, "name": "Weiler", "country": "DE", "coord": {"lon": 7.08333, "lat": 50.150002}}, {"id": 2946411, "name": "Bonscheuer", "country": "DE", "coord": {"lon": 8.03333, "lat": 50.26667}}, {"id": 2938213, "name": "Dennweiler", "country": "DE", "coord": {"lon": 7.38333, "lat": 49.583328}}, {"id": 6554875, "name": "Stein-Bockenheim", "country": "DE", "coord": {"lon": 7.96667, "lat": 49.766701}}, {"id": 2828386, "name": "Stein-Bockenheim", "country": "DE", "coord": {"lon": 7.96667, "lat": 49.76667}}, {"id": 6556964, "name": "N\u00fcdlingen", "country": "DE", "coord": {"lon": 10.125, "lat": 50.221699}}, {"id": 2861695, "name": "Nudlingen", "country": "DE", "coord": {"lon": 10.1, "lat": 50.23333}}, {"id": 6556981, "name": "Hollstadt", "country": "DE", "coord": {"lon": 10.3, "lat": 50.349998}}, {"id": 2900375, "name": "Hollstadt", "country": "DE", "coord": {"lon": 10.3, "lat": 50.349998}}, {"id": 6553444, "name": "Sch\u00fcrdt", "country": "DE", "coord": {"lon": 7.55, "lat": 50.666698}}, {"id": 2835683, "name": "Schurdt", "country": "DE", "coord": {"lon": 7.55, "lat": 50.666672}}, {"id": 2936861, "name": "Dippach", "country": "DE", "coord": {"lon": 10.7, "lat": 49.799999}}, {"id": 2829474, "name": "Starkenschwind", "country": "DE", "coord": {"lon": 10.98461, "lat": 49.972969}}, {"id": 2939302, "name": "Dallackenried", "country": "DE", "coord": {"lon": 11.91656, "lat": 49.152748}}, {"id": 2848209, "name": "Renholding", "country": "DE", "coord": {"lon": 13.3, "lat": 48.683331}}, {"id": 2904755, "name": "Hilgenreit", "country": "DE", "coord": {"lon": 13.25943, "lat": 48.849892}}, {"id": 6551462, "name": "Klempau", "country": "DE", "coord": {"lon": 10.6667, "lat": 53.766701}}, {"id": 2887918, "name": "Klempau", "country": "DE", "coord": {"lon": 10.66667, "lat": 53.76667}}, {"id": 2939663, "name": "Curslack", "country": "DE", "coord": {"lon": 10.23333, "lat": 53.450001}}, {"id": 2865648, "name": "Neuenkamp", "country": "DE", "coord": {"lon": 8.88333, "lat": 53.599998}}, {"id": 2951479, "name": "Behnsdorf", "country": "DE", "coord": {"lon": 11.15, "lat": 52.316669}}, {"id": 2892192, "name": "Katzenelnbogen", "country": "DE", "coord": {"lon": 7.95, "lat": 50.283329}}, {"id": 2955543, "name": "Armsfeld", "country": "DE", "coord": {"lon": 9.06667, "lat": 51.049999}}, {"id": 6554512, "name": "Usch", "country": "DE", "coord": {"lon": 6.6, "lat": 50.099998}}, {"id": 2818115, "name": "Usch", "country": "DE", "coord": {"lon": 6.6, "lat": 50.099998}}, {"id": 6553806, "name": "N\u00f6rtershausen", "country": "DE", "coord": {"lon": 7.48333, "lat": 50.216702}}, {"id": 2861815, "name": "Nortershausen", "country": "DE", "coord": {"lon": 7.48333, "lat": 50.216671}}, {"id": 6557221, "name": "Oberostendorf", "country": "DE", "coord": {"lon": 10.75, "lat": 47.9333}}, {"id": 2859465, "name": "Oberostendorf", "country": "DE", "coord": {"lon": 10.75, "lat": 47.933331}}, {"id": 2916659, "name": "Gro\u00dfenbornholt", "country": "DE", "coord": {"lon": 9.33333, "lat": 54.099998}}, {"id": 2904963, "name": "Heuwisch", "country": "DE", "coord": {"lon": 8.96667, "lat": 54.23333}}, {"id": 6551473, "name": "Labenz", "country": "DE", "coord": {"lon": 10.5167, "lat": 53.700001}}, {"id": 2882073, "name": "Labenz", "country": "DE", "coord": {"lon": 10.51667, "lat": 53.700001}}, {"id": 2870275, "name": "M\u00f6ckers", "country": "DE", "coord": {"lon": 10.4, "lat": 50.716671}}, {"id": 6554653, "name": "Neroth", "country": "DE", "coord": {"lon": 6.75, "lat": 50.200001}}, {"id": 2866477, "name": "Neroth", "country": "DE", "coord": {"lon": 6.74689, "lat": 50.196018}}, {"id": 6553569, "name": "Achtelsbach", "country": "DE", "coord": {"lon": 7.08333, "lat": 49.616699}}, {"id": 2959655, "name": "Achtelsbach", "country": "DE", "coord": {"lon": 7.08333, "lat": 49.616669}}, {"id": 6553984, "name": "W\u00fcrrich", "country": "DE", "coord": {"lon": 7.3, "lat": 49.983299}}, {"id": 2805652, "name": "Wurrich", "country": "DE", "coord": {"lon": 7.3, "lat": 49.98333}}, {"id": 2864369, "name": "Neu Plaue", "country": "DE", "coord": {"lon": 12.4, "lat": 52.433331}}, {"id": 2895283, "name": "Jahnsfelde", "country": "DE", "coord": {"lon": 14.23333, "lat": 52.51667}}, {"id": 6547845, "name": "Nossendorf", "country": "DE", "coord": {"lon": 12.95, "lat": 53.966702}}, {"id": 2861787, "name": "Nossendorf", "country": "DE", "coord": {"lon": 12.95932, "lat": 53.96209}}, {"id": 6548279, "name": "Koserow", "country": "DE", "coord": {"lon": 14.0251, "lat": 54.029701}}, {"id": 2885338, "name": "Koserow", "country": "DE", "coord": {"lon": 14, "lat": 54.049999}}, {"id": 6555036, "name": "Heiligenmoschel", "country": "DE", "coord": {"lon": 7.76667, "lat": 49.549999}}, {"id": 2907561, "name": "Heiligenmoschel", "country": "DE", "coord": {"lon": 7.76667, "lat": 49.549999}}, {"id": 6555148, "name": "Schellweiler", "country": "DE", "coord": {"lon": 7.4, "lat": 49.516701}}, {"id": 2839791, "name": "Schellweiler", "country": "DE", "coord": {"lon": 7.4, "lat": 49.51667}}, {"id": 6555047, "name": "Mehlbach", "country": "DE", "coord": {"lon": 7.71667, "lat": 49.516701}}, {"id": 2872449, "name": "Mehlbach", "country": "DE", "coord": {"lon": 7.71667, "lat": 49.51667}}, {"id": 6555066, "name": "Lambsborn", "country": "DE", "coord": {"lon": 7.43333, "lat": 49.366699}}, {"id": 2881768, "name": "Lambsborn", "country": "DE", "coord": {"lon": 7.43333, "lat": 49.366669}}, {"id": 2814714, "name": "Walkes", "country": "DE", "coord": {"lon": 9.95, "lat": 50.633331}}, {"id": 2896782, "name": "Ibra", "country": "DE", "coord": {"lon": 9.48333, "lat": 50.816669}}, {"id": 2887942, "name": "Klein Ziethen", "country": "DE", "coord": {"lon": 13.45, "lat": 52.383331}}, {"id": 2934406, "name": "D\u00fcrrbrunn", "country": "DE", "coord": {"lon": 11.15713, "lat": 49.83577}}, {"id": 2818957, "name": "Unterostendorf", "country": "DE", "coord": {"lon": 10.73333, "lat": 47.950001}}, {"id": 6557159, "name": "Gl\u00f6tt", "country": "DE", "coord": {"lon": 10.4833, "lat": 48.5}}, {"id": 2919792, "name": "Glott", "country": "DE", "coord": {"lon": 10.48333, "lat": 48.5}}, {"id": 2928885, "name": "Espa", "country": "DE", "coord": {"lon": 8.59577, "lat": 50.42263}}, {"id": 2843342, "name": "Ruensiek", "country": "DE", "coord": {"lon": 9.17161, "lat": 51.865261}}, {"id": 6553615, "name": "Mittelreidenbach", "country": "DE", "coord": {"lon": 7.45, "lat": 49.733299}}, {"id": 2870612, "name": "Mittelreidenbach", "country": "DE", "coord": {"lon": 7.45, "lat": 49.73333}}, {"id": 6554464, "name": "Messerich", "country": "DE", "coord": {"lon": 6.48333, "lat": 49.9333}}, {"id": 2871621, "name": "Messerich", "country": "DE", "coord": {"lon": 6.48333, "lat": 49.933331}}, {"id": 2855178, "name": "Paunsdorf", "country": "DE", "coord": {"lon": 12.45, "lat": 51.349998}}, {"id": 2847213, "name": "Rieder", "country": "DE", "coord": {"lon": 10.65, "lat": 47.75}}, {"id": 2869802, "name": "Mondorf", "country": "DE", "coord": {"lon": 7.06667, "lat": 50.783329}}, {"id": 2843324, "name": "Landkreis R\u00fcgen", "country": "DE", "coord": {"lon": 13.39361, "lat": 54.455002}}, {"id": 6548428, "name": "Ralswiek", "country": "DE", "coord": {"lon": 13.45, "lat": 54.466702}}, {"id": 2850735, "name": "Ralswiek", "country": "DE", "coord": {"lon": 13.45, "lat": 54.466671}}, {"id": 6552631, "name": "G\u00f6denstorf", "country": "DE", "coord": {"lon": 10.12349, "lat": 53.22855}}, {"id": 2919569, "name": "Godenstorf", "country": "DE", "coord": {"lon": 10.12349, "lat": 53.22855}}, {"id": 2870148, "name": "M\u00f6hren", "country": "DE", "coord": {"lon": 10.88333, "lat": 48.933331}}, {"id": 6556372, "name": "Pfaffing", "country": "DE", "coord": {"lon": 12.1167, "lat": 48.049999}}, {"id": 2854310, "name": "Pfaffing", "country": "DE", "coord": {"lon": 12.10917, "lat": 48.054562}}, {"id": 6551505, "name": "Sierksrade", "country": "DE", "coord": {"lon": 10.6, "lat": 53.733299}}, {"id": 2832337, "name": "Sierksrade", "country": "DE", "coord": {"lon": 10.6, "lat": 53.73333}}, {"id": 2946550, "name": "Bombeck", "country": "DE", "coord": {"lon": 7.35, "lat": 51.98333}}, {"id": 2876401, "name": "Lohausen", "country": "DE", "coord": {"lon": 6.73333, "lat": 51.26667}}, {"id": 2850688, "name": "Ramholz", "country": "DE", "coord": {"lon": 9.61063, "lat": 50.33144}}, {"id": 6556723, "name": "Pechbrunn", "country": "DE", "coord": {"lon": 12.1667, "lat": 49.966702}}, {"id": 2855145, "name": "Pechbrunn", "country": "DE", "coord": {"lon": 12.16667, "lat": 49.966671}}, {"id": 2862782, "name": "Niederviehbig", "country": "DE", "coord": {"lon": 14.76667, "lat": 50.916672}}, {"id": 2806963, "name": "Woldegk", "country": "DE", "coord": {"lon": 13.58333, "lat": 53.466671}}, {"id": 2813974, "name": "Wartberg", "country": "DE", "coord": {"lon": 13.45, "lat": 48.783329}}, {"id": 2918127, "name": "Grana", "country": "DE", "coord": {"lon": 12.11667, "lat": 51.049999}}, {"id": 2850286, "name": "Rassau", "country": "DE", "coord": {"lon": 10.69004, "lat": 52.957169}}, {"id": 2873252, "name": "Marlishausen", "country": "DE", "coord": {"lon": 11.01667, "lat": 50.816669}}, {"id": 2861629, "name": "Nusplingen", "country": "DE", "coord": {"lon": 9.10161, "lat": 48.118179}}, {"id": 2940696, "name": "B\u00fc\u00dffeld", "country": "DE", "coord": {"lon": 9, "lat": 50.700001}}, {"id": 2873616, "name": "Marienbrunn", "country": "DE", "coord": {"lon": 9.57806, "lat": 49.862499}}, {"id": 2815594, "name": "Wackersleben", "country": "DE", "coord": {"lon": 11.01667, "lat": 52.066669}}, {"id": 6555357, "name": "Steinalben", "country": "DE", "coord": {"lon": 7.65, "lat": 49.3167}}, {"id": 2828879, "name": "Steinalben", "country": "DE", "coord": {"lon": 7.65, "lat": 49.316669}}, {"id": 2938344, "name": "Delligsen", "country": "DE", "coord": {"lon": 9.80272, "lat": 51.9412}}, {"id": 2810384, "name": "Westerengel", "country": "DE", "coord": {"lon": 10.9, "lat": 51.283329}}, {"id": 2932321, "name": "Eichendorf", "country": "DE", "coord": {"lon": 12.85, "lat": 48.633331}}, {"id": 6548276, "name": "Klein B\u00fcnzow", "country": "DE", "coord": {"lon": 13.6333, "lat": 53.9333}}, {"id": 2889642, "name": "Klein Bunzow", "country": "DE", "coord": {"lon": 13.63333, "lat": 53.933331}}, {"id": 6557079, "name": "Erlabrunn", "country": "DE", "coord": {"lon": 9.84417, "lat": 49.859699}}, {"id": 2929594, "name": "Erlabrunn", "country": "DE", "coord": {"lon": 9.84417, "lat": 49.859718}}, {"id": 2901358, "name": "Hohenwarthe", "country": "DE", "coord": {"lon": 11.71667, "lat": 52.23333}}, {"id": 2858791, "name": "Obertheres", "country": "DE", "coord": {"lon": 10.43333, "lat": 50.01667}}, {"id": 2848608, "name": "Reischach", "country": "DE", "coord": {"lon": 12.21512, "lat": 47.897301}}, {"id": 2818213, "name": "Urexweiler", "country": "DE", "coord": {"lon": 7.07811, "lat": 49.428059}}, {"id": 6554514, "name": "Wallendorf", "country": "DE", "coord": {"lon": 6.3, "lat": 49.866699}}, {"id": 2814643, "name": "Wallendorf", "country": "DE", "coord": {"lon": 6.3, "lat": 49.866669}}, {"id": 6557140, "name": "Kleinaitingen", "country": "DE", "coord": {"lon": 10.8333, "lat": 48.216702}}, {"id": 2889814, "name": "Kleinaitingen", "country": "DE", "coord": {"lon": 10.83333, "lat": 48.216671}}, {"id": 2822939, "name": "Tharandt", "country": "DE", "coord": {"lon": 13.58333, "lat": 50.98333}}, {"id": 2941515, "name": "Burg", "country": "DE", "coord": {"lon": 11.0574, "lat": 49.08157}}, {"id": 6552430, "name": "Winnigstedt", "country": "DE", "coord": {"lon": 10.7667, "lat": 52.0667}}, {"id": 2807862, "name": "Winnigstedt", "country": "DE", "coord": {"lon": 10.76879, "lat": 52.066292}}, {"id": 2866351, "name": "Nettelkamp", "country": "DE", "coord": {"lon": 10.58333, "lat": 52.883331}}, {"id": 6552425, "name": "Semmenstedt", "country": "DE", "coord": {"lon": 10.7, "lat": 52.099998}}, {"id": 2833099, "name": "Semmenstedt", "country": "DE", "coord": {"lon": 10.69691, "lat": 52.09375}}, {"id": 6552431, "name": "Wittmar", "country": "DE", "coord": {"lon": 10.6333, "lat": 52.133301}}, {"id": 2807229, "name": "Wittmar", "country": "DE", "coord": {"lon": 10.64, "lat": 52.129688}}, {"id": 2896639, "name": "Ihlowerfehn", "country": "DE", "coord": {"lon": 7.43333, "lat": 53.400002}}, {"id": 2927351, "name": "Feldkirchen", "country": "DE", "coord": {"lon": 12.96667, "lat": 47.799999}}, {"id": 2885916, "name": "K\u00f6nigsberg in Bayern", "country": "DE", "coord": {"lon": 10.58333, "lat": 50.083328}}, {"id": 2895269, "name": "Jahrstedt", "country": "DE", "coord": {"lon": 10.97672, "lat": 52.56007}}, {"id": 2863087, "name": "Niedernberg", "country": "DE", "coord": {"lon": 12.05, "lat": 50.299999}}, {"id": 6556608, "name": "Moosthenning", "country": "DE", "coord": {"lon": 12.49875, "lat": 48.677078}}, {"id": 2869325, "name": "Moosthenning", "country": "DE", "coord": {"lon": 12.5, "lat": 48.683331}}, {"id": 6557280, "name": "Genderkingen", "country": "DE", "coord": {"lon": 10.8833, "lat": 48.700001}}, {"id": 2921371, "name": "Genderkingen", "country": "DE", "coord": {"lon": 10.88333, "lat": 48.700001}}, {"id": 6556670, "name": "Bechtsrieth", "country": "DE", "coord": {"lon": 12.2167, "lat": 49.650002}}, {"id": 2951732, "name": "Bechtsrieth", "country": "DE", "coord": {"lon": 12.20997, "lat": 49.644871}}, {"id": 2945314, "name": "Brandheide", "country": "DE", "coord": {"lon": 9.06667, "lat": 52.866669}}, {"id": 6551588, "name": "Olderup", "country": "DE", "coord": {"lon": 9.11667, "lat": 54.533298}}, {"id": 2857399, "name": "Olderup", "country": "DE", "coord": {"lon": 9.11667, "lat": 54.533329}}, {"id": 2898155, "name": "Hubing", "country": "DE", "coord": {"lon": 12.86714, "lat": 48.870869}}, {"id": 2898917, "name": "Horn", "country": "DE", "coord": {"lon": 10.08989, "lat": 53.554062}}, {"id": 6557114, "name": "Hollenbach", "country": "DE", "coord": {"lon": 11.0667, "lat": 48.483299}}, {"id": 2900590, "name": "Hollenbach", "country": "DE", "coord": {"lon": 11.06667, "lat": 48.48333}}, {"id": 2925581, "name": "Frankenhofen", "country": "DE", "coord": {"lon": 10.75, "lat": 47.883331}}, {"id": 2837887, "name": "Schmiddorf", "country": "DE", "coord": {"lon": 12.03333, "lat": 48.783329}}, {"id": 2956098, "name": "Angering", "country": "DE", "coord": {"lon": 13.31037, "lat": 48.365601}}, {"id": 6556245, "name": "Ohlstadt", "country": "DE", "coord": {"lon": 11.2333, "lat": 47.633301}}, {"id": 2857649, "name": "Ohlstadt", "country": "DE", "coord": {"lon": 11.23333, "lat": 47.633331}}, {"id": 6551470, "name": "Kuddew\u00f6rde", "country": "DE", "coord": {"lon": 10.4, "lat": 53.583302}}, {"id": 2883066, "name": "Kuddeworde", "country": "DE", "coord": {"lon": 10.4, "lat": 53.583328}}, {"id": 6551688, "name": "Heist", "country": "DE", "coord": {"lon": 9.65, "lat": 53.650002}}, {"id": 2907111, "name": "Heist", "country": "DE", "coord": {"lon": 9.65, "lat": 53.650002}}, {"id": 6548736, "name": "Wiednitz", "country": "DE", "coord": {"lon": 14.0333, "lat": 51.400002}}, {"id": 2809550, "name": "Wiednitz", "country": "DE", "coord": {"lon": 14.03333, "lat": 51.400002}}, {"id": 6548770, "name": "Borsdorf", "country": "DE", "coord": {"lon": 12.5458, "lat": 51.355598}}, {"id": 2946016, "name": "Borsdorf", "country": "DE", "coord": {"lon": 12.53333, "lat": 51.349998}}, {"id": 2867707, "name": "Munchenbernsdorf", "country": "DE", "coord": {"lon": 11.93333, "lat": 50.816669}}, {"id": 2876739, "name": "Labejum", "country": "DE", "coord": {"lon": 11.9, "lat": 51.633331}}, {"id": 2921164, "name": "Gerbstedt", "country": "DE", "coord": {"lon": 11.61667, "lat": 51.633331}}, {"id": 2950072, "name": "Salzlandkreis", "country": "DE", "coord": {"lon": 11.73917, "lat": 51.75806}}, {"id": 6550919, "name": "Egeln, Stadt", "country": "DE", "coord": {"lon": 11.4333, "lat": 51.950001}}, {"id": 2933256, "name": "Egeln", "country": "DE", "coord": {"lon": 11.43265, "lat": 51.94384}}, {"id": 2920850, "name": "Gerwisch", "country": "DE", "coord": {"lon": 11.75, "lat": 52.166672}}, {"id": 6552782, "name": "Apensen", "country": "DE", "coord": {"lon": 9.61355, "lat": 53.431702}}, {"id": 2955815, "name": "Apensen", "country": "DE", "coord": {"lon": 9.61667, "lat": 53.433331}}, {"id": 6552633, "name": "Handeloh", "country": "DE", "coord": {"lon": 9.83923, "lat": 53.245628}}, {"id": 2910992, "name": "Handeloh", "country": "DE", "coord": {"lon": 9.83923, "lat": 53.245628}}, {"id": 6552573, "name": "Belum", "country": "DE", "coord": {"lon": 9, "lat": 53.8167}}, {"id": 2951147, "name": "Belum", "country": "DE", "coord": {"lon": 9, "lat": 53.816669}}, {"id": 2828994, "name": "Steilshoop", "country": "DE", "coord": {"lon": 10.05917, "lat": 53.610279}}, {"id": 6548198, "name": "L\u00fcbow", "country": "DE", "coord": {"lon": 11.5167, "lat": 53.849998}}, {"id": 2875577, "name": "Lubow", "country": "DE", "coord": {"lon": 11.51667, "lat": 53.849998}}, {"id": 6552373, "name": "S\u00fcpplingen", "country": "DE", "coord": {"lon": 10.9167, "lat": 52.233299}}, {"id": 2824603, "name": "Supplingen", "country": "DE", "coord": {"lon": 10.90393, "lat": 52.228111}}, {"id": 6552331, "name": "Wesendorf", "country": "DE", "coord": {"lon": 10.5333, "lat": 52.599998}}, {"id": 2810659, "name": "Wesendorf", "country": "DE", "coord": {"lon": 10.53333, "lat": 52.599998}}, {"id": 2830885, "name": "Sottmar", "country": "DE", "coord": {"lon": 10.61743, "lat": 52.12569}}, {"id": 2806940, "name": "Wolfartsweier", "country": "DE", "coord": {"lon": 8.45673, "lat": 48.976501}}, {"id": 2874486, "name": "Mahlberg", "country": "DE", "coord": {"lon": 7.81411, "lat": 48.286388}}, {"id": 2843498, "name": "R\u00fcckersdorf", "country": "DE", "coord": {"lon": 10.73333, "lat": 49.26667}}, {"id": 2926426, "name": "Flachslanden", "country": "DE", "coord": {"lon": 10.51667, "lat": 49.400002}}, {"id": 2862306, "name": "N\u00f6dlitz", "country": "DE", "coord": {"lon": 12.08333, "lat": 51.133331}}, {"id": 6552763, "name": "Wohnste", "country": "DE", "coord": {"lon": 9.53333, "lat": 53.349998}}, {"id": 2807010, "name": "Wohnste", "country": "DE", "coord": {"lon": 9.53333, "lat": 53.349998}}, {"id": 6555458, "name": "Gammelshausen", "country": "DE", "coord": {"lon": 9.65063, "lat": 48.64048}}, {"id": 2922753, "name": "Gammelshausen", "country": "DE", "coord": {"lon": 9.65072, "lat": 48.640228}}, {"id": 6555492, "name": "Walheim", "country": "DE", "coord": {"lon": 9.15111, "lat": 49.014198}}, {"id": 2814747, "name": "Walheim", "country": "DE", "coord": {"lon": 9.15111, "lat": 49.014172}}, {"id": 6556001, "name": "Achstetten", "country": "DE", "coord": {"lon": 9.9, "lat": 48.266701}}, {"id": 2959659, "name": "Achstetten", "country": "DE", "coord": {"lon": 9.9, "lat": 48.26667}}, {"id": 6555427, "name": "Neidlingen", "country": "DE", "coord": {"lon": 9.56446, "lat": 48.57859}}, {"id": 2866593, "name": "Neidlingen", "country": "DE", "coord": {"lon": 9.56454, "lat": 48.578651}}, {"id": 2905063, "name": "Heuchlingen", "country": "DE", "coord": {"lon": 10.1, "lat": 48.583328}}, {"id": 6552528, "name": "Hoyerhagen", "country": "DE", "coord": {"lon": 9.08564, "lat": 52.828899}}, {"id": 2898312, "name": "Hoyerhagen", "country": "DE", "coord": {"lon": 9.08333, "lat": 52.833328}}, {"id": 6552672, "name": "Boitze", "country": "DE", "coord": {"lon": 10.75, "lat": 53.150002}}, {"id": 2946830, "name": "Boitze", "country": "DE", "coord": {"lon": 10.75, "lat": 53.150002}}, {"id": 6552561, "name": "Hohne", "country": "DE", "coord": {"lon": 10.3667, "lat": 52.583302}}, {"id": 2900881, "name": "Hohne", "country": "DE", "coord": {"lon": 10.36667, "lat": 52.583328}}, {"id": 2941159, "name": "Burgsinn", "country": "DE", "coord": {"lon": 9.65, "lat": 50.150002}}, {"id": 2842597, "name": "Sabershausen", "country": "DE", "coord": {"lon": 7.41667, "lat": 50.116669}}, {"id": 6557071, "name": "Sulzheim", "country": "DE", "coord": {"lon": 10.3333, "lat": 49.950001}}, {"id": 2824729, "name": "Sulzheim", "country": "DE", "coord": {"lon": 10.33333, "lat": 49.950001}}, {"id": 6552697, "name": "Vastorf", "country": "DE", "coord": {"lon": 10.55, "lat": 53.200001}}, {"id": 2817823, "name": "Vastorf", "country": "DE", "coord": {"lon": 10.54563, "lat": 53.198009}}, {"id": 6548028, "name": "Wulkenzin", "country": "DE", "coord": {"lon": 13.1667, "lat": 53.533298}}, {"id": 2805865, "name": "Wulkenzin", "country": "DE", "coord": {"lon": 13.16667, "lat": 53.533329}}, {"id": 6548005, "name": "Hohenzieritz", "country": "DE", "coord": {"lon": 13.1, "lat": 53.450001}}, {"id": 2901324, "name": "Hohenzieritz", "country": "DE", "coord": {"lon": 13.09811, "lat": 53.442371}}, {"id": 6548065, "name": "Kargow", "country": "DE", "coord": {"lon": 12.75, "lat": 53.5}}, {"id": 2892951, "name": "Kargow", "country": "DE", "coord": {"lon": 12.75, "lat": 53.5}}, {"id": 6548007, "name": "Klein Vielen", "country": "DE", "coord": {"lon": 13.0333, "lat": 53.450001}}, {"id": 2888078, "name": "Klein Vielen", "country": "DE", "coord": {"lon": 13.02755, "lat": 53.452492}}, {"id": 2888111, "name": "Klein Trebel", "country": "DE", "coord": {"lon": 11.31667, "lat": 53}}, {"id": 6553163, "name": "Bickenbach", "country": "DE", "coord": {"lon": 8.6099, "lat": 49.745602}}, {"id": 2949296, "name": "Bickenbach", "country": "DE", "coord": {"lon": 8.6175, "lat": 49.759171}}, {"id": 3208092, "name": "Marborn", "country": "DE", "coord": {"lon": 9.41667, "lat": 50.316669}}, {"id": 2920874, "name": "Gerterode", "country": "DE", "coord": {"lon": 9.68333, "lat": 50.933331}}, {"id": 2936169, "name": "Dorchheim", "country": "DE", "coord": {"lon": 8.06667, "lat": 50.5}}, {"id": 2814860, "name": "Waldmannshausen", "country": "DE", "coord": {"lon": 8.06667, "lat": 50.51667}}, {"id": 6554060, "name": "Lohrheim", "country": "DE", "coord": {"lon": 8.05, "lat": 50.3167}}, {"id": 2876127, "name": "Lohrheim", "country": "DE", "coord": {"lon": 8.05, "lat": 50.316669}}, {"id": 6553227, "name": "Villmar", "country": "DE", "coord": {"lon": 8.2, "lat": 50.383301}}, {"id": 2817217, "name": "Villmar", "country": "DE", "coord": {"lon": 8.2, "lat": 50.383331}}, {"id": 2934697, "name": "Duingen", "country": "DE", "coord": {"lon": 9.69578, "lat": 52.00449}}, {"id": 6552859, "name": "Berumbur", "country": "DE", "coord": {"lon": 7.31121, "lat": 53.589298}}, {"id": 2949855, "name": "Berumbur", "country": "DE", "coord": {"lon": 7.31667, "lat": 53.599998}}, {"id": 2917826, "name": "Greetsiel", "country": "DE", "coord": {"lon": 7.1, "lat": 53.5}}, {"id": 6552912, "name": "Niederlangen", "country": "DE", "coord": {"lon": 7.28333, "lat": 52.849998}}, {"id": 2863185, "name": "Niederlangen", "country": "DE", "coord": {"lon": 7.28333, "lat": 52.849998}}, {"id": 2807525, "name": "Wirschweiler", "country": "DE", "coord": {"lon": 7.18333, "lat": 49.76667}}, {"id": 2807526, "name": "Wirschweiler", "country": "DE", "coord": {"lon": 7.16667, "lat": 49.76667}}, {"id": 2930229, "name": "Engelsdorf", "country": "DE", "coord": {"lon": 6.25, "lat": 50.033329}}, {"id": 2837317, "name": "Schneppenbach", "country": "DE", "coord": {"lon": 7.23333, "lat": 49.849998}}, {"id": 6553726, "name": "Sosberg", "country": "DE", "coord": {"lon": 7.33333, "lat": 50.083302}}, {"id": 2830910, "name": "Sosberg", "country": "DE", "coord": {"lon": 7.33333, "lat": 50.083328}}, {"id": 2859228, "name": "Oberrothan", "country": "DE", "coord": {"lon": 10.6, "lat": 48.23333}}, {"id": 6557123, "name": "Sielenbach", "country": "DE", "coord": {"lon": 11.1667, "lat": 48.400002}}, {"id": 2832392, "name": "Sielenbach", "country": "DE", "coord": {"lon": 11.16667, "lat": 48.400002}}, {"id": 2836407, "name": "Schopfloch", "country": "DE", "coord": {"lon": 10.3, "lat": 49.116669}}, {"id": 6556732, "name": "Frensdorf", "country": "DE", "coord": {"lon": 10.8667, "lat": 49.8167}}, {"id": 2924983, "name": "Frensdorf", "country": "DE", "coord": {"lon": 10.86667, "lat": 49.816669}}, {"id": 2953916, "name": "Autenhausen", "country": "DE", "coord": {"lon": 10.78333, "lat": 50.23333}}, {"id": 2780898, "name": "Dobl", "country": "AT", "coord": {"lon": 13.44589, "lat": 48.469219}}, {"id": 2808110, "name": "Windorf", "country": "DE", "coord": {"lon": 12.78333, "lat": 48.450001}}, {"id": 6547502, "name": "Otzing", "country": "DE", "coord": {"lon": 12.8167, "lat": 48.766701}}, {"id": 2855902, "name": "Otzing", "country": "DE", "coord": {"lon": 12.81667, "lat": 48.76667}}, {"id": 6557064, "name": "Niederwerrn", "country": "DE", "coord": {"lon": 10.1833, "lat": 50.0667}}, {"id": 2862733, "name": "Niederwerrn", "country": "DE", "coord": {"lon": 10.1827, "lat": 50.061489}}, {"id": 2911364, "name": "Hambach", "country": "DE", "coord": {"lon": 10.21667, "lat": 50.099998}}, {"id": 6555997, "name": "Westerheim", "country": "DE", "coord": {"lon": 9.62487, "lat": 48.516102}}, {"id": 2810336, "name": "Westerheim", "country": "DE", "coord": {"lon": 9.62424, "lat": 48.51511}}, {"id": 6553874, "name": "Beltheim", "country": "DE", "coord": {"lon": 7.45, "lat": 50.099998}}, {"id": 2951151, "name": "Beltheim", "country": "DE", "coord": {"lon": 7.45, "lat": 50.099998}}, {"id": 6554884, "name": "W\u00f6llstein", "country": "DE", "coord": {"lon": 7.96667, "lat": 49.8167}}, {"id": 2806353, "name": "Wollstein", "country": "DE", "coord": {"lon": 7.96667, "lat": 49.816669}}, {"id": 6554874, "name": "Spiesheim", "country": "DE", "coord": {"lon": 8.1275, "lat": 49.810299}}, {"id": 2830449, "name": "Spiesheim", "country": "DE", "coord": {"lon": 8.1275, "lat": 49.81028}}, {"id": 2825716, "name": "Stromberg", "country": "DE", "coord": {"lon": 7.77286, "lat": 49.94389}}, {"id": 2918920, "name": "G\u00f6rsroth", "country": "DE", "coord": {"lon": 8.21667, "lat": 50.216671}}, {"id": 2837689, "name": "Schmittweiler", "country": "DE", "coord": {"lon": 7.33784, "lat": 49.410191}}, {"id": 6555296, "name": "Ockenheim", "country": "DE", "coord": {"lon": 7.96667, "lat": 49.9333}}, {"id": 2858239, "name": "Ockenheim", "country": "DE", "coord": {"lon": 7.97127, "lat": 49.94371}}, {"id": 2880211, "name": "Lauchroden", "country": "DE", "coord": {"lon": 10.16667, "lat": 50.98333}}, {"id": 6549760, "name": "B\u00fcttstedt", "country": "DE", "coord": {"lon": 10.3, "lat": 51.25}}, {"id": 2940516, "name": "Buttstedt", "country": "DE", "coord": {"lon": 10.3, "lat": 51.25}}, {"id": 2883507, "name": "Krottorf", "country": "DE", "coord": {"lon": 11.18333, "lat": 51.966671}}, {"id": 2878986, "name": "Leitzkau", "country": "DE", "coord": {"lon": 11.95, "lat": 52.049999}}, {"id": 2820452, "name": "Uenglingen", "country": "DE", "coord": {"lon": 11.8, "lat": 52.616669}}, {"id": 2927214, "name": "Felsenberg", "country": "DE", "coord": {"lon": 11.51667, "lat": 52.183331}}, {"id": 2824255, "name": "Tangerhutte", "country": "DE", "coord": {"lon": 11.8, "lat": 52.433331}}, {"id": 2860932, "name": "Oberelsbach", "country": "DE", "coord": {"lon": 10.13333, "lat": 50.433331}}, {"id": 2929165, "name": "Eschau", "country": "DE", "coord": {"lon": 9.2575, "lat": 49.82}}, {"id": 2848309, "name": "Remlingen", "country": "DE", "coord": {"lon": 9.69444, "lat": 49.804722}}, {"id": 2940315, "name": "Caputh", "country": "DE", "coord": {"lon": 13, "lat": 52.349998}}, {"id": 2808674, "name": "Wilhelmshorst", "country": "DE", "coord": {"lon": 13.06667, "lat": 52.333328}}, {"id": 2882208, "name": "K\u00fctten", "country": "DE", "coord": {"lon": 12, "lat": 51.583328}}, {"id": 2885524, "name": "K\u00f6rbelitz", "country": "DE", "coord": {"lon": 11.78333, "lat": 52.183331}}, {"id": 6552692, "name": "Scharnebeck", "country": "DE", "coord": {"lon": 10.5167, "lat": 53.299999}}, {"id": 2840297, "name": "Scharnebeck", "country": "DE", "coord": {"lon": 10.51667, "lat": 53.299999}}, {"id": 6552801, "name": "Himmelpforten", "country": "DE", "coord": {"lon": 9.30517, "lat": 53.614128}}, {"id": 2904543, "name": "Himmelpforten", "country": "DE", "coord": {"lon": 9.30516, "lat": 53.614128}}, {"id": 2900840, "name": "Hohnstorf", "country": "DE", "coord": {"lon": 10.53486, "lat": 53.144562}}, {"id": 6551622, "name": "Vi\u00f6l", "country": "DE", "coord": {"lon": 9.1419, "lat": 54.5816}}, {"id": 2817154, "name": "Viol", "country": "DE", "coord": {"lon": 9.18333, "lat": 54.566669}}, {"id": 6551797, "name": "Aukrug", "country": "DE", "coord": {"lon": 9.78333, "lat": 54.083302}}, {"id": 3208536, "name": "Aukrug", "country": "DE", "coord": {"lon": 9.78333, "lat": 54.083328}}, {"id": 6551982, "name": "Norderstapel", "country": "DE", "coord": {"lon": 9.25, "lat": 54.349998}}, {"id": 2862027, "name": "Norderstapel", "country": "DE", "coord": {"lon": 9.25, "lat": 54.349998}}, {"id": 2807301, "name": "Wittenwurth", "country": "DE", "coord": {"lon": 9.05, "lat": 54.26667}}, {"id": 6551387, "name": "Weddingstedt", "country": "DE", "coord": {"lon": 9.1, "lat": 54.233299}}, {"id": 2813468, "name": "Weddingstedt", "country": "DE", "coord": {"lon": 9.1, "lat": 54.23333}}, {"id": 2949489, "name": "Bevern", "country": "DE", "coord": {"lon": 9.49408, "lat": 51.858261}}, {"id": 2852858, "name": "Polle", "country": "DE", "coord": {"lon": 9.4, "lat": 51.900002}}, {"id": 6557387, "name": "Uslar, Stadt", "country": "DE", "coord": {"lon": 9.65, "lat": 51.666698}}, {"id": 2929009, "name": "Eschershausen", "country": "DE", "coord": {"lon": 9.63535, "lat": 51.678089}}, {"id": 2910652, "name": "Hardenberg", "country": "DE", "coord": {"lon": 7.08333, "lat": 51.316669}}, {"id": 6553812, "name": "Weitersburg", "country": "DE", "coord": {"lon": 7.6, "lat": 50.416698}}, {"id": 2811652, "name": "Weitersburg", "country": "DE", "coord": {"lon": 7.6, "lat": 50.416672}}, {"id": 6556029, "name": "Tannheim", "country": "DE", "coord": {"lon": 10.0833, "lat": 48}}, {"id": 2824053, "name": "Tannheim", "country": "DE", "coord": {"lon": 10.08333, "lat": 48}}, {"id": 6552521, "name": "Binnen", "country": "DE", "coord": {"lon": 9.13327, "lat": 52.619099}}, {"id": 2948810, "name": "Binnen", "country": "DE", "coord": {"lon": 9.13333, "lat": 52.616669}}, {"id": 2943712, "name": "Br\u00f6\u00dfnitz", "country": "DE", "coord": {"lon": 13.66667, "lat": 51.366669}}, {"id": 6557003, "name": "Pfarrweisach", "country": "DE", "coord": {"lon": 10.7333, "lat": 50.150002}}, {"id": 2854167, "name": "Pfarrweisach", "country": "DE", "coord": {"lon": 10.73333, "lat": 50.150002}}, {"id": 6552790, "name": "Dollern", "country": "DE", "coord": {"lon": 9.5497, "lat": 53.535099}}, {"id": 2936369, "name": "Dollern", "country": "DE", "coord": {"lon": 9.55, "lat": 53.533329}}, {"id": 2907343, "name": "Heinbockel", "country": "DE", "coord": {"lon": 9.33333, "lat": 53.583328}}, {"id": 2864053, "name": "Neustadt bei Coburg", "country": "DE", "coord": {"lon": 11.11667, "lat": 50.316669}}, {"id": 2859458, "name": "Oberottmarshausen", "country": "DE", "coord": {"lon": 10.85, "lat": 48.23333}}, {"id": 6556336, "name": "Gachenbach", "country": "DE", "coord": {"lon": 11.2333, "lat": 48.5}}, {"id": 2923426, "name": "Gachenbach", "country": "DE", "coord": {"lon": 11.23333, "lat": 48.5}}, {"id": 6557269, "name": "Alerheim", "country": "DE", "coord": {"lon": 10.6167, "lat": 48.849998}}, {"id": 2958560, "name": "Alerheim", "country": "DE", "coord": {"lon": 10.61667, "lat": 48.849998}}, {"id": 2959080, "name": "Ahrensdorf", "country": "DE", "coord": {"lon": 14.08333, "lat": 52.166672}}, {"id": 2895618, "name": "Issing", "country": "DE", "coord": {"lon": 10.95, "lat": 47.950001}}, {"id": 6556309, "name": "Brunnthal", "country": "DE", "coord": {"lon": 11.6833, "lat": 48.016701}}, {"id": 2943074, "name": "Brunnthal", "country": "DE", "coord": {"lon": 11.68405, "lat": 48.006519}}, {"id": 3205579, "name": "Schalbruch", "country": "DE", "coord": {"lon": 5.9, "lat": 51.049999}}, {"id": 6555576, "name": "Bartholom\u00e4", "country": "DE", "coord": {"lon": 9.98743, "lat": 48.753361}}, {"id": 2952359, "name": "Bartholoma", "country": "DE", "coord": {"lon": 9.98752, "lat": 48.753502}}, {"id": 6553257, "name": "Nentershausen", "country": "DE", "coord": {"lon": 9.93333, "lat": 51.016701}}, {"id": 2866511, "name": "Nentershausen", "country": "DE", "coord": {"lon": 9.93333, "lat": 51.01667}}, {"id": 2807757, "name": "Winterhausen", "country": "DE", "coord": {"lon": 10.01661, "lat": 49.706829}}, {"id": 2814815, "name": "Waldsassen", "country": "DE", "coord": {"lon": 12.30278, "lat": 50.005001}}, {"id": 6548504, "name": "Niederfrohna", "country": "DE", "coord": {"lon": 12.7167, "lat": 50.900002}}, {"id": 2863429, "name": "Niederfrohna", "country": "DE", "coord": {"lon": 12.71667, "lat": 50.900002}}, {"id": 2924186, "name": "Frontenhausen", "country": "DE", "coord": {"lon": 12.53333, "lat": 48.549999}}, {"id": 6552909, "name": "Messingen", "country": "DE", "coord": {"lon": 7.46667, "lat": 52.466702}}, {"id": 2871613, "name": "Messingen", "country": "DE", "coord": {"lon": 7.46667, "lat": 52.466671}}, {"id": 6552703, "name": "Axstedt", "country": "DE", "coord": {"lon": 8.76667, "lat": 53.349998}}, {"id": 2953840, "name": "Axstedt", "country": "DE", "coord": {"lon": 8.76667, "lat": 53.349998}}, {"id": 2827932, "name": "Steinhude", "country": "DE", "coord": {"lon": 9.35, "lat": 52.450001}}, {"id": 6558450, "name": "Lindhorst", "country": "DE", "coord": {"lon": 9.287, "lat": 52.357899}}, {"id": 2877171, "name": "Lindhorst", "country": "DE", "coord": {"lon": 9.28333, "lat": 52.366669}}, {"id": 6552413, "name": "Gielde", "country": "DE", "coord": {"lon": 10.5, "lat": 52.033298}}, {"id": 2920632, "name": "Gielde", "country": "DE", "coord": {"lon": 10.49366, "lat": 52.036228}}, {"id": 2828971, "name": "Steimke", "country": "DE", "coord": {"lon": 10.60215, "lat": 52.74622}}, {"id": 6552304, "name": "Dedelstorf", "country": "DE", "coord": {"lon": 10.5, "lat": 52.700001}}, {"id": 2938619, "name": "Dedelstorf", "country": "DE", "coord": {"lon": 10.5, "lat": 52.700001}}, {"id": 2934898, "name": "Dr\u00f6gennottorf", "country": "DE", "coord": {"lon": 10.65, "lat": 53.099998}}, {"id": 2820183, "name": "Ummeln", "country": "DE", "coord": {"lon": 8.45, "lat": 51.966671}}, {"id": 6552459, "name": "Schwarme", "country": "DE", "coord": {"lon": 9.01667, "lat": 52.900002}}, {"id": 2835223, "name": "Schwarme", "country": "DE", "coord": {"lon": 9.01667, "lat": 52.900002}}, {"id": 2956756, "name": "Altwildungen", "country": "DE", "coord": {"lon": 9.12749, "lat": 51.126419}}, {"id": 6547801, "name": "Thelkow", "country": "DE", "coord": {"lon": 12.5667, "lat": 54.033298}}, {"id": 2822870, "name": "Thelkow", "country": "DE", "coord": {"lon": 12.55978, "lat": 54.03616}}, {"id": 2948950, "name": "Billenhagen", "country": "DE", "coord": {"lon": 12.35816, "lat": 54.12352}}, {"id": 6548176, "name": "Dragun", "country": "DE", "coord": {"lon": 11.2167, "lat": 53.700001}}, {"id": 2935365, "name": "Dragun", "country": "DE", "coord": {"lon": 11.21667, "lat": 53.700001}}, {"id": 2849263, "name": "Rehna", "country": "DE", "coord": {"lon": 11.05, "lat": 53.783329}}, {"id": 6548239, "name": "Bobitz", "country": "DE", "coord": {"lon": 11.35, "lat": 53.799999}}, {"id": 2947447, "name": "Bobitz", "country": "DE", "coord": {"lon": 11.35, "lat": 53.799999}}, {"id": 2875558, "name": "Lubz", "country": "DE", "coord": {"lon": 12.02917, "lat": 53.462608}}, {"id": 2817610, "name": "Venzkow", "country": "DE", "coord": {"lon": 11.7, "lat": 53.650002}}, {"id": 2854700, "name": "Petersberg", "country": "DE", "coord": {"lon": 11.55, "lat": 53.599998}}, {"id": 6547883, "name": "Gutow", "country": "DE", "coord": {"lon": 12.1333, "lat": 53.766701}}, {"id": 2913335, "name": "Gutow", "country": "DE", "coord": {"lon": 12.13543, "lat": 53.759979}}, {"id": 2864705, "name": "Neukloster", "country": "DE", "coord": {"lon": 11.7, "lat": 53.866669}}, {"id": 2807106, "name": "Woez", "country": "DE", "coord": {"lon": 11.08744, "lat": 53.591381}}, {"id": 6551493, "name": "Sahms", "country": "DE", "coord": {"lon": 10.5333, "lat": 53.533298}}, {"id": 2842372, "name": "Sahms", "country": "DE", "coord": {"lon": 10.53333, "lat": 53.533329}}, {"id": 6551404, "name": "Alt M\u00f6lln", "country": "DE", "coord": {"lon": 10.65, "lat": 53.616699}}, {"id": 2956985, "name": "Alt Molln", "country": "DE", "coord": {"lon": 10.65, "lat": 53.616669}}, {"id": 2880399, "name": "Lasbek", "country": "DE", "coord": {"lon": 10.33333, "lat": 53.75}}, {"id": 2880400, "name": "Lasbek", "country": "DE", "coord": {"lon": 10.36667, "lat": 53.73333}}, {"id": 6551469, "name": "Krummesse", "country": "DE", "coord": {"lon": 10.65, "lat": 53.783298}}, {"id": 2883270, "name": "Krummesse", "country": "DE", "coord": {"lon": 10.65, "lat": 53.783329}}, {"id": 6551465, "name": "Kollow", "country": "DE", "coord": {"lon": 10.4667, "lat": 53.466702}}, {"id": 2886278, "name": "Kollow", "country": "DE", "coord": {"lon": 10.46667, "lat": 53.466671}}, {"id": 6551423, "name": "Dalldorf", "country": "DE", "coord": {"lon": 10.61193, "lat": 53.43475}}, {"id": 2939293, "name": "Dalldorf", "country": "DE", "coord": {"lon": 10.61185, "lat": 53.435001}}, {"id": 6551629, "name": "Winnert", "country": "DE", "coord": {"lon": 9.2, "lat": 54.4333}}, {"id": 2807864, "name": "Winnert", "country": "DE", "coord": {"lon": 9.2, "lat": 54.433331}}, {"id": 6551852, "name": "Hamweddel", "country": "DE", "coord": {"lon": 9.61667, "lat": 54.1833}}, {"id": 2911010, "name": "Hamweddel", "country": "DE", "coord": {"lon": 9.61667, "lat": 54.183331}}, {"id": 2944892, "name": "Bredenmoor", "country": "DE", "coord": {"lon": 9.9, "lat": 54.333328}}, {"id": 6551909, "name": "Rieseby", "country": "DE", "coord": {"lon": 9.81667, "lat": 54.533298}}, {"id": 2846922, "name": "Rieseby", "country": "DE", "coord": {"lon": 9.81667, "lat": 54.533329}}, {"id": 6551937, "name": "Wattenbek", "country": "DE", "coord": {"lon": 10.05, "lat": 54.166698}}, {"id": 2813647, "name": "Wattenbek", "country": "DE", "coord": {"lon": 10.05, "lat": 54.166672}}, {"id": 6552642, "name": "Marschacht", "country": "DE", "coord": {"lon": 10.37524, "lat": 53.415199}}, {"id": 3209070, "name": "Marschacht", "country": "DE", "coord": {"lon": 10.37524, "lat": 53.415199}}, {"id": 6552622, "name": "Bendestorf", "country": "DE", "coord": {"lon": 9.9843, "lat": 53.335602}}, {"id": 2951115, "name": "Bendestorf", "country": "DE", "coord": {"lon": 9.96667, "lat": 53.349998}}, {"id": 2877203, "name": "Lindewitt", "country": "DE", "coord": {"lon": 9.21667, "lat": 54.716671}}, {"id": 2877204, "name": "Lindewitt", "country": "DE", "coord": {"lon": 9.2, "lat": 54.700001}}, {"id": 2840399, "name": "Scharam", "country": "DE", "coord": {"lon": 12.63333, "lat": 47.799999}}, {"id": 2897875, "name": "Huldsessen", "country": "DE", "coord": {"lon": 12.7, "lat": 48.400002}}, {"id": 2904870, "name": "Hidring", "country": "DE", "coord": {"lon": 13.31667, "lat": 48.633331}}, {"id": 2913296, "name": "Gutwiesen", "country": "DE", "coord": {"lon": 13.5, "lat": 48.666672}}, {"id": 6556474, "name": "Hohenau", "country": "DE", "coord": {"lon": 13.4833, "lat": 48.849998}}, {"id": 3205010, "name": "Hohenau", "country": "DE", "coord": {"lon": 13.48825, "lat": 48.849831}}, {"id": 6556528, "name": "Kirchham", "country": "DE", "coord": {"lon": 13.26659, "lat": 48.346722}}, {"id": 2890499, "name": "Kirchham", "country": "DE", "coord": {"lon": 13.26719, "lat": 48.346378}}, {"id": 2855050, "name": "Peigerting", "country": "DE", "coord": {"lon": 13.33333, "lat": 48.716671}}, {"id": 2828438, "name": "Steinberg", "country": "DE", "coord": {"lon": 10.01667, "lat": 50.299999}}, {"id": 2918284, "name": "Grafenried", "country": "DE", "coord": {"lon": 13.01185, "lat": 49.095619}}, {"id": 2904317, "name": "Hinterbuchberg", "country": "DE", "coord": {"lon": 12.68333, "lat": 48.966671}}, {"id": 2926973, "name": "Fichten", "country": "DE", "coord": {"lon": 12.55, "lat": 49.133331}}, {"id": 2883782, "name": "Landkreis Kronach", "country": "DE", "coord": {"lon": 11.39861, "lat": 50.318062}}, {"id": 6556814, "name": "Wilhelmsthal", "country": "DE", "coord": {"lon": 11.3806, "lat": 50.320099}}, {"id": 2808657, "name": "Wilhelmsthal", "country": "DE", "coord": {"lon": 11.36667, "lat": 50.299999}}, {"id": 2825429, "name": "Stuhlingen", "country": "DE", "coord": {"lon": 8.43333, "lat": 47.73333}}, {"id": 6557122, "name": "Schmiechen", "country": "DE", "coord": {"lon": 10.9667, "lat": 48.216702}}, {"id": 2837809, "name": "Schmiechen", "country": "DE", "coord": {"lon": 10.96667, "lat": 48.216671}}, {"id": 6556067, "name": "Ho\u00dfkirch", "country": "DE", "coord": {"lon": 9.45, "lat": 47.950001}}, {"id": 2898458, "name": "Hosskirch", "country": "DE", "coord": {"lon": 9.45, "lat": 47.950001}}, {"id": 6556087, "name": "Leibertingen", "country": "DE", "coord": {"lon": 9.01454, "lat": 48.04274}}, {"id": 2879335, "name": "Leibertingen", "country": "DE", "coord": {"lon": 9.1, "lat": 48.049999}}, {"id": 6555548, "name": "B\u00fchlerzell", "country": "DE", "coord": {"lon": 9.92056, "lat": 49.0033}}, {"id": 2941923, "name": "Buhlerzell", "country": "DE", "coord": {"lon": 9.92056, "lat": 49.00333}}, {"id": 2807790, "name": "Winterberg", "country": "DE", "coord": {"lon": 10.1038, "lat": 49.032581}}, {"id": 6553665, "name": "Briedel", "country": "DE", "coord": {"lon": 7.15, "lat": 50.016701}}, {"id": 2944146, "name": "Briedel", "country": "DE", "coord": {"lon": 7.15, "lat": 50.01667}}, {"id": 6554357, "name": "Neumagen-Dhron", "country": "DE", "coord": {"lon": 6.88333, "lat": 49.849998}}, {"id": 3207532, "name": "Neumagen-Dhron", "country": "DE", "coord": {"lon": 6.88333, "lat": 49.849998}}, {"id": 6555324, "name": "Hauenstein", "country": "DE", "coord": {"lon": 7.85437, "lat": 49.192051}}, {"id": 2909129, "name": "Hauenstein", "country": "DE", "coord": {"lon": 7.85492, "lat": 49.192108}}, {"id": 2859756, "name": "Obermohr", "country": "DE", "coord": {"lon": 7.5, "lat": 49.466671}}, {"id": 2867094, "name": "Nanzweiler", "country": "DE", "coord": {"lon": 7.43333, "lat": 49.450001}}, {"id": 6555026, "name": "Bann", "country": "DE", "coord": {"lon": 7.61667, "lat": 49.383301}}, {"id": 2952934, "name": "Bann", "country": "DE", "coord": {"lon": 7.61667, "lat": 49.383331}}, {"id": 6555125, "name": "Nanzdietschweiler", "country": "DE", "coord": {"lon": 7.45, "lat": 49.450001}}, {"id": 2867098, "name": "Nanzdietschweiler", "country": "DE", "coord": {"lon": 7.45, "lat": 49.450001}}, {"id": 6554956, "name": "Imsweiler", "country": "DE", "coord": {"lon": 7.8, "lat": 49.599998}}, {"id": 2896156, "name": "Imsweiler", "country": "DE", "coord": {"lon": 7.8, "lat": 49.599998}}, {"id": 2835304, "name": "Schwanden", "country": "DE", "coord": {"lon": 7.53333, "lat": 49.48333}}, {"id": 6552363, "name": "Grasleben", "country": "DE", "coord": {"lon": 11.01585, "lat": 52.306541}}, {"id": 2917991, "name": "Grasleben", "country": "DE", "coord": {"lon": 11.01465, "lat": 52.306381}}, {"id": 2931182, "name": "Elfershausen", "country": "DE", "coord": {"lon": 9.96151, "lat": 50.14743}}, {"id": 2859916, "name": "Oberlengsfeld", "country": "DE", "coord": {"lon": 9.85, "lat": 50.816669}}, {"id": 2908570, "name": "Hayna", "country": "DE", "coord": {"lon": 8.20333, "lat": 49.11972}}, {"id": 2959508, "name": "Adelsheim", "country": "DE", "coord": {"lon": 9.39333, "lat": 49.40361}}, {"id": 2878351, "name": "Leun", "country": "DE", "coord": {"lon": 8.35836, "lat": 50.551289}}, {"id": 2848541, "name": "Reiskirchen", "country": "DE", "coord": {"lon": 8.51046, "lat": 50.50404}}, {"id": 6554244, "name": "M\u00f6rlen", "country": "DE", "coord": {"lon": 7.88333, "lat": 50.700001}}, {"id": 2869222, "name": "Morlen", "country": "DE", "coord": {"lon": 7.88333, "lat": 50.700001}}, {"id": 6553781, "name": "Saffig", "country": "DE", "coord": {"lon": 7.41667, "lat": 50.383301}}, {"id": 2842438, "name": "Saffig", "country": "DE", "coord": {"lon": 7.41667, "lat": 50.383331}}, {"id": 6554147, "name": "Hundsdorf", "country": "DE", "coord": {"lon": 7.71667, "lat": 50.466702}}, {"id": 2897518, "name": "Hundsdorf", "country": "DE", "coord": {"lon": 7.71667, "lat": 50.466671}}, {"id": 6553335, "name": "Reifferscheid", "country": "DE", "coord": {"lon": 6.88333, "lat": 50.400002}}, {"id": 2848914, "name": "Reifferscheid", "country": "DE", "coord": {"lon": 6.88499, "lat": 50.405289}}, {"id": 6553354, "name": "Wassenach", "country": "DE", "coord": {"lon": 7.28333, "lat": 50.4333}}, {"id": 2813787, "name": "Wassenach", "country": "DE", "coord": {"lon": 7.28333, "lat": 50.433331}}, {"id": 6554644, "name": "Katzwinkel", "country": "DE", "coord": {"lon": 6.91667, "lat": 50.25}}, {"id": 2892104, "name": "Katzwinkel", "country": "DE", "coord": {"lon": 6.91667, "lat": 50.25}}, {"id": 2950083, "name": "Bernbach", "country": "DE", "coord": {"lon": 9.14509, "lat": 50.154469}}, {"id": 6548615, "name": "K\u00f6nigswartha", "country": "DE", "coord": {"lon": 14.3333, "lat": 51.3167}}, {"id": 2885742, "name": "Konigswartha", "country": "DE", "coord": {"lon": 14.33333, "lat": 51.316669}}, {"id": 2864402, "name": "Ninive", "country": "DE", "coord": {"lon": 14.71667, "lat": 51}}, {"id": 2949857, "name": "Bertsdorf", "country": "DE", "coord": {"lon": 14.73333, "lat": 50.883331}}, {"id": 2882361, "name": "Kurbersdorf", "country": "DE", "coord": {"lon": 11.9, "lat": 49.799999}}, {"id": 2855956, "name": "Ottmannsdorf", "country": "DE", "coord": {"lon": 11.85, "lat": 50.783329}}, {"id": 2805623, "name": "Wurzbach", "country": "DE", "coord": {"lon": 11.53333, "lat": 50.466671}}, {"id": 2874652, "name": "M\u00e4bendorf", "country": "DE", "coord": {"lon": 10.6, "lat": 50.599998}}, {"id": 6550337, "name": "Unterwei\u00dfbach", "country": "DE", "coord": {"lon": 11.1833, "lat": 50.616699}}, {"id": 2818426, "name": "Unterweissbach", "country": "DE", "coord": {"lon": 11.16743, "lat": 50.61396}}, {"id": 6550315, "name": "Dr\u00f6bischau", "country": "DE", "coord": {"lon": 11.0667, "lat": 50.633301}}, {"id": 2934921, "name": "Drobischau", "country": "DE", "coord": {"lon": 11.06667, "lat": 50.633331}}, {"id": 6549288, "name": "Wolmirsleben", "country": "DE", "coord": {"lon": 11.4833, "lat": 51.950001}}, {"id": 2806343, "name": "Wolmirsleben", "country": "DE", "coord": {"lon": 11.48333, "lat": 51.950001}}, {"id": 2949103, "name": "Biere", "country": "DE", "coord": {"lon": 11.65443, "lat": 51.974312}}, {"id": 2895536, "name": "Ivenrode", "country": "DE", "coord": {"lon": 11.23129, "lat": 52.272781}}, {"id": 2913449, "name": "Gusten", "country": "DE", "coord": {"lon": 11.6, "lat": 51.783329}}, {"id": 2911725, "name": "Hakeborn", "country": "DE", "coord": {"lon": 11.36667, "lat": 51.916672}}, {"id": 2908726, "name": "Hausneindorf", "country": "DE", "coord": {"lon": 11.27227, "lat": 51.840099}}, {"id": 2851450, "name": "Quellendorf", "country": "DE", "coord": {"lon": 12.13333, "lat": 51.75}}, {"id": 2825372, "name": "Stumsdorf", "country": "DE", "coord": {"lon": 12.06667, "lat": 51.616669}}, {"id": 2946357, "name": "Borau", "country": "DE", "coord": {"lon": 12, "lat": 51.200001}}, {"id": 2918092, "name": "Granschutz", "country": "DE", "coord": {"lon": 12.05, "lat": 51.183331}}, {"id": 2883895, "name": "Krina", "country": "DE", "coord": {"lon": 12.48333, "lat": 51.650002}}, {"id": 6549077, "name": "Helbra", "country": "DE", "coord": {"lon": 11.5, "lat": 51.549999}}, {"id": 2907018, "name": "Helbra", "country": "DE", "coord": {"lon": 11.5, "lat": 51.549999}}, {"id": 2941053, "name": "Burgwerben", "country": "DE", "coord": {"lon": 11.98333, "lat": 51.216671}}, {"id": 2951531, "name": "Beesenstedt", "country": "DE", "coord": {"lon": 11.73333, "lat": 51.566669}}, {"id": 2908374, "name": "Hedersleben", "country": "DE", "coord": {"lon": 11.65, "lat": 51.549999}}, {"id": 6549919, "name": "Herbsleben", "country": "DE", "coord": {"lon": 10.8333, "lat": 51.116699}}, {"id": 2906185, "name": "Herbsleben", "country": "DE", "coord": {"lon": 10.83333, "lat": 51.116669}}, {"id": 2838600, "name": "Schleusingen", "country": "DE", "coord": {"lon": 10.75, "lat": 50.51667}}, {"id": 2918251, "name": "Gr\u00e4finau-Angstedt", "country": "DE", "coord": {"lon": 11.01667, "lat": 50.700001}}, {"id": 6550214, "name": "M\u00f6hrenbach", "country": "DE", "coord": {"lon": 11, "lat": 50.633301}}, {"id": 2870147, "name": "Mohrenbach", "country": "DE", "coord": {"lon": 11, "lat": 50.633331}}, {"id": 2839284, "name": "Schilderhain", "country": "DE", "coord": {"lon": 12.93333, "lat": 51.450001}}, {"id": 2914848, "name": "Gro\u00dfwig", "country": "DE", "coord": {"lon": 12.88333, "lat": 51.566669}}, {"id": 6548776, "name": "Machern", "country": "DE", "coord": {"lon": 12.6099, "lat": 51.362801}}, {"id": 2874642, "name": "Machern", "country": "DE", "coord": {"lon": 12.63333, "lat": 51.366669}}, {"id": 6548006, "name": "Holldorf", "country": "DE", "coord": {"lon": 13.2667, "lat": 53.466702}}, {"id": 2900639, "name": "Holldorf", "country": "DE", "coord": {"lon": 13.26667, "lat": 53.466671}}, {"id": 6548464, "name": "Liepgarten", "country": "DE", "coord": {"lon": 14.0167, "lat": 53.716702}}, {"id": 2877803, "name": "Liepgarten", "country": "DE", "coord": {"lon": 14.01667, "lat": 53.716671}}, {"id": 6554747, "name": "Irsch", "country": "DE", "coord": {"lon": 6.6, "lat": 49.599998}}, {"id": 2895756, "name": "Irsch", "country": "DE", "coord": {"lon": 6.6, "lat": 49.599998}}, {"id": 6552900, "name": "L\u00e4hden", "country": "DE", "coord": {"lon": 7.56667, "lat": 52.75}}, {"id": 2881921, "name": "Lahden", "country": "DE", "coord": {"lon": 7.56667, "lat": 52.75}}, {"id": 6552891, "name": "Gersten", "country": "DE", "coord": {"lon": 7.51667, "lat": 52.583302}}, {"id": 2920914, "name": "Gersten", "country": "DE", "coord": {"lon": 7.51667, "lat": 52.583328}}, {"id": 6552751, "name": "Selsingen", "country": "DE", "coord": {"lon": 9.2167, "lat": 53.376202}}, {"id": 2833154, "name": "Selsingen", "country": "DE", "coord": {"lon": 9.21289, "lat": 53.373291}}, {"id": 6552959, "name": "Schwerinsdorf", "country": "DE", "coord": {"lon": 7.68333, "lat": 53.3167}}, {"id": 2834271, "name": "Schwerinsdorf", "country": "DE", "coord": {"lon": 7.68333, "lat": 53.316669}}, {"id": 2874979, "name": "Lust", "country": "DE", "coord": {"lon": 9.68333, "lat": 52.616669}}, {"id": 6558466, "name": "Jameln", "country": "DE", "coord": {"lon": 11.0471, "lat": 53.041302}}, {"id": 2895226, "name": "Jameln", "country": "DE", "coord": {"lon": 11.08333, "lat": 53.049999}}, {"id": 2957095, "name": "Alt Jabel", "country": "DE", "coord": {"lon": 11.16667, "lat": 53.25}}, {"id": 6551394, "name": "Westerdeichstrich", "country": "DE", "coord": {"lon": 8.86667, "lat": 54.166698}}, {"id": 2810399, "name": "Westerdeichstrich", "country": "DE", "coord": {"lon": 8.86667, "lat": 54.166672}}, {"id": 6554076, "name": "Oberbachheim", "country": "DE", "coord": {"lon": 7.75, "lat": 50.25}}, {"id": 2861340, "name": "Oberbachheim", "country": "DE", "coord": {"lon": 7.75, "lat": 50.25}}, {"id": 2825056, "name": "S\u00fcderzollhaus", "country": "DE", "coord": {"lon": 9.28333, "lat": 54.650002}}, {"id": 2890662, "name": "Kirchberg", "country": "DE", "coord": {"lon": 13.18333, "lat": 48.900002}}, {"id": 2882575, "name": "Kulsheim", "country": "DE", "coord": {"lon": 9.5225, "lat": 49.66972}}, {"id": 2873960, "name": "Manebach", "country": "DE", "coord": {"lon": 10.86667, "lat": 50.683331}}, {"id": 6552324, "name": "Tappenbeck", "country": "DE", "coord": {"lon": 10.75, "lat": 52.466702}}, {"id": 2824000, "name": "Tappenbeck", "country": "DE", "coord": {"lon": 10.74068, "lat": 52.470551}}, {"id": 2911283, "name": "Hamdorf", "country": "DE", "coord": {"lon": 10.28333, "lat": 53.98333}}, {"id": 6551915, "name": "Schmalstede", "country": "DE", "coord": {"lon": 10.0333, "lat": 54.200001}}, {"id": 2838040, "name": "Schmalstede", "country": "DE", "coord": {"lon": 10.03333, "lat": 54.200001}}, {"id": 6551799, "name": "Bargstedt", "country": "DE", "coord": {"lon": 9.76667, "lat": 54.166698}}, {"id": 2952636, "name": "Bargstedt", "country": "DE", "coord": {"lon": 9.76667, "lat": 54.166672}}, {"id": 6554010, "name": "Dahlheim", "country": "DE", "coord": {"lon": 7.7, "lat": 50.200001}}, {"id": 2939405, "name": "Dahlheim", "country": "DE", "coord": {"lon": 7.7, "lat": 50.200001}}, {"id": 2898108, "name": "Huckelriede", "country": "DE", "coord": {"lon": 8.81275, "lat": 53.056068}}, {"id": 6556605, "name": "Mamming", "country": "DE", "coord": {"lon": 12.6, "lat": 48.650002}}, {"id": 2874000, "name": "Mamming", "country": "DE", "coord": {"lon": 12.6, "lat": 48.650002}}, {"id": 6556551, "name": "Prackenbach", "country": "DE", "coord": {"lon": 12.8333, "lat": 49.099998}}, {"id": 2852372, "name": "Prackenbach", "country": "DE", "coord": {"lon": 12.83333, "lat": 49.099998}}, {"id": 2874446, "name": "Mahlwinkel", "country": "DE", "coord": {"lon": 11.78333, "lat": 52.400002}}, {"id": 2856262, "name": "Ostingersleben", "country": "DE", "coord": {"lon": 11.17035, "lat": 52.211079}}, {"id": 6549640, "name": "Beetzendorf", "country": "DE", "coord": {"lon": 11.1, "lat": 52.700001}}, {"id": 2951522, "name": "Beetzendorf", "country": "DE", "coord": {"lon": 11.1, "lat": 52.700001}}, {"id": 2854666, "name": "Petersfehn", "country": "DE", "coord": {"lon": 8.11667, "lat": 53.133331}}, {"id": 2886262, "name": "Kolmbach", "country": "DE", "coord": {"lon": 8.75389, "lat": 49.708061}}, {"id": 6554849, "name": "Gabsheim", "country": "DE", "coord": {"lon": 8.17611, "lat": 49.827801}}, {"id": 2923428, "name": "Gabsheim", "country": "DE", "coord": {"lon": 8.17611, "lat": 49.827782}}, {"id": 6553315, "name": "Kaltenborn", "country": "DE", "coord": {"lon": 7.01667, "lat": 50.400002}}, {"id": 2893622, "name": "Kaltenborn", "country": "DE", "coord": {"lon": 7.01667, "lat": 50.400002}}, {"id": 2864653, "name": "Neu Kuppritz", "country": "DE", "coord": {"lon": 14.58333, "lat": 51.150002}}, {"id": 2949949, "name": "Bernstadt", "country": "DE", "coord": {"lon": 14.85, "lat": 51.049999}}, {"id": 2865525, "name": "Neuer Anbau", "country": "DE", "coord": {"lon": 12.76667, "lat": 50.466671}}, {"id": 2925760, "name": "Forsth\u00e4user", "country": "DE", "coord": {"lon": 12.96667, "lat": 50.683331}}, {"id": 2875553, "name": "Luchau", "country": "DE", "coord": {"lon": 13.75, "lat": 50.866669}}, {"id": 6549753, "name": "Berlingerode", "country": "DE", "coord": {"lon": 10.2333, "lat": 51.466702}}, {"id": 2950139, "name": "Berlingerode", "country": "DE", "coord": {"lon": 10.2384, "lat": 51.457748}}, {"id": 6550199, "name": "Elxleben", "country": "DE", "coord": {"lon": 11.05, "lat": 50.866699}}, {"id": 2930631, "name": "Elxleben", "country": "DE", "coord": {"lon": 11.05, "lat": 50.866669}}, {"id": 2890880, "name": "Kindelbruck", "country": "DE", "coord": {"lon": 11.08333, "lat": 51.26667}}, {"id": 2903720, "name": "Hirschberg", "country": "DE", "coord": {"lon": 11.81667, "lat": 50.400002}}, {"id": 2852400, "name": "Pouch", "country": "DE", "coord": {"lon": 12.40133, "lat": 51.623241}}, {"id": 2852995, "name": "Pohl", "country": "DE", "coord": {"lon": 12.33333, "lat": 50.400002}}, {"id": 2950226, "name": "Bergzow", "country": "DE", "coord": {"lon": 12.05, "lat": 52.400002}}, {"id": 2837385, "name": "Schneidlingen", "country": "DE", "coord": {"lon": 11.46667, "lat": 51.900002}}, {"id": 2823973, "name": "Tarthun", "country": "DE", "coord": {"lon": 11.46667, "lat": 51.933331}}, {"id": 2841264, "name": "Satuelle", "country": "DE", "coord": {"lon": 11.38333, "lat": 52.333328}}, {"id": 2886203, "name": "Kolonie Breiteiche", "country": "DE", "coord": {"lon": 11.21859, "lat": 52.455589}}, {"id": 2818057, "name": "Uthm\u00f6den", "country": "DE", "coord": {"lon": 11.3554, "lat": 52.354012}}, {"id": 2891811, "name": "Keller", "country": "DE", "coord": {"lon": 10.35, "lat": 47.599998}}, {"id": 2959514, "name": "Adelsdorf", "country": "DE", "coord": {"lon": 10.68333, "lat": 49.48333}}, {"id": 2915349, "name": "Grosslangheim", "country": "DE", "coord": {"lon": 10.23333, "lat": 49.75}}, {"id": 6555141, "name": "Rehweiler", "country": "DE", "coord": {"lon": 7.43333, "lat": 49.483299}}, {"id": 2849232, "name": "Rehweiler", "country": "DE", "coord": {"lon": 7.43333, "lat": 49.48333}}, {"id": 6555370, "name": "Dellfeld", "country": "DE", "coord": {"lon": 7.48333, "lat": 49.233299}}, {"id": 2938351, "name": "Dellfeld", "country": "DE", "coord": {"lon": 7.48333, "lat": 49.23333}}, {"id": 2950117, "name": "Bermersbach", "country": "DE", "coord": {"lon": 8.35, "lat": 48.683331}}, {"id": 6555867, "name": "\u00d6hningen", "country": "DE", "coord": {"lon": 8.9, "lat": 47.666698}}, {"id": 2857610, "name": "Ohningen", "country": "DE", "coord": {"lon": 8.9, "lat": 47.666672}}, {"id": 2908575, "name": "Hayingen", "country": "DE", "coord": {"lon": 9.4776, "lat": 48.275311}}, {"id": 2807263, "name": "Wittigenhagen", "country": "DE", "coord": {"lon": 8.85, "lat": 52.049999}}, {"id": 2878366, "name": "Leudersdorf", "country": "DE", "coord": {"lon": 6.75, "lat": 50.349998}}, {"id": 2860962, "name": "Obereip", "country": "DE", "coord": {"lon": 7.45238, "lat": 50.719608}}, {"id": 6548162, "name": "Barnekow", "country": "DE", "coord": {"lon": 11.3667, "lat": 53.866699}}, {"id": 2952511, "name": "Barnekow", "country": "DE", "coord": {"lon": 11.36667, "lat": 53.866669}}, {"id": 2816495, "name": "Vorbeck", "country": "DE", "coord": {"lon": 11.58225, "lat": 53.643089}}, {"id": 2836290, "name": "Schorssow", "country": "DE", "coord": {"lon": 12.56613, "lat": 53.683441}}, {"id": 2952659, "name": "Bargeshagen", "country": "DE", "coord": {"lon": 11.98458, "lat": 54.11161}}, {"id": 2815793, "name": "Waat", "country": "DE", "coord": {"lon": 6.49575, "lat": 51.145432}}, {"id": 6549785, "name": "Hohes Kreuz", "country": "DE", "coord": {"lon": 10.1, "lat": 51.416698}}, {"id": 2825936, "name": "Streitholz", "country": "DE", "coord": {"lon": 10.09137, "lat": 51.4142}}, {"id": 2838628, "name": "Schlettau", "country": "DE", "coord": {"lon": 12.95, "lat": 50.566669}}, {"id": 2819002, "name": "Unterneuhausen", "country": "DE", "coord": {"lon": 12, "lat": 48.616669}}, {"id": 2817806, "name": "Veckenstedt", "country": "DE", "coord": {"lon": 10.73333, "lat": 51.900002}}, {"id": 6556742, "name": "Pettstadt", "country": "DE", "coord": {"lon": 10.92719, "lat": 49.829842}}, {"id": 2854557, "name": "Pettstadt", "country": "DE", "coord": {"lon": 10.92839, "lat": 49.82996}}, {"id": 6554801, "name": "Trassem", "country": "DE", "coord": {"lon": 6.51667, "lat": 49.5667}}, {"id": 2821548, "name": "Trassem", "country": "DE", "coord": {"lon": 6.51667, "lat": 49.566669}}, {"id": 6554167, "name": "\u00d6tzingen", "country": "DE", "coord": {"lon": 7.83333, "lat": 50.5}}, {"id": 2855901, "name": "Otzingen", "country": "DE", "coord": {"lon": 7.83333, "lat": 50.5}}, {"id": 6553551, "name": "Volxheim", "country": "DE", "coord": {"lon": 7.93333, "lat": 49.8167}}, {"id": 2816524, "name": "Volxheim", "country": "DE", "coord": {"lon": 7.93333, "lat": 49.816669}}, {"id": 2927107, "name": "Fernhag", "country": "DE", "coord": {"lon": 11.45, "lat": 48.5}}, {"id": 2830595, "name": "Spesbach", "country": "DE", "coord": {"lon": 7.5, "lat": 49.433331}}, {"id": 2826661, "name": "Stockum", "country": "DE", "coord": {"lon": 7.9, "lat": 50.616669}}, {"id": 2958052, "name": "Altbrandsleben", "country": "DE", "coord": {"lon": 11.25, "lat": 52.066669}}, {"id": 6548791, "name": "Trossin", "country": "DE", "coord": {"lon": 12.8167, "lat": 51.616699}}, {"id": 2820974, "name": "Trossin", "country": "DE", "coord": {"lon": 12.81667, "lat": 51.616669}}, {"id": 2819020, "name": "Unternaundorf", "country": "DE", "coord": {"lon": 13.66699, "lat": 50.84779}}, {"id": 2958049, "name": "Alt Buchhorst", "country": "DE", "coord": {"lon": 13.85, "lat": 52.433331}}, {"id": 6557059, "name": "Gochsheim", "country": "DE", "coord": {"lon": 10.27597, "lat": 50.021568}}, {"id": 2919620, "name": "Gochsheim", "country": "DE", "coord": {"lon": 10.28333, "lat": 50.01667}}, {"id": 6556967, "name": "Ramsthal", "country": "DE", "coord": {"lon": 10.0667, "lat": 50.133301}}, {"id": 2850535, "name": "Ramsthal", "country": "DE", "coord": {"lon": 10.06777, "lat": 50.140388}}, {"id": 6554181, "name": "Vielbach", "country": "DE", "coord": {"lon": 7.76667, "lat": 50.516701}}, {"id": 2817410, "name": "Vielbach", "country": "DE", "coord": {"lon": 7.76667, "lat": 50.51667}}, {"id": 2832722, "name": "Siebenborn", "country": "DE", "coord": {"lon": 7.63333, "lat": 50.26667}}, {"id": 2861261, "name": "Oberbieber", "country": "DE", "coord": {"lon": 7.5, "lat": 50.48333}}, {"id": 2886851, "name": "Kodden", "country": "DE", "coord": {"lon": 7.4, "lat": 50.616669}}, {"id": 6553722, "name": "Sankt Aldegund", "country": "DE", "coord": {"lon": 7.13333, "lat": 50.083302}}, {"id": 2841673, "name": "Sankt Aldegund", "country": "DE", "coord": {"lon": 7.13333, "lat": 50.083328}}, {"id": 6554800, "name": "Thomm", "country": "DE", "coord": {"lon": 6.8, "lat": 49.733299}}, {"id": 2822684, "name": "Thomm", "country": "DE", "coord": {"lon": 6.8, "lat": 49.73333}}, {"id": 2814559, "name": "Wallitz", "country": "DE", "coord": {"lon": 12.76667, "lat": 53.116669}}, {"id": 6548178, "name": "Glasin", "country": "DE", "coord": {"lon": 11.7333, "lat": 53.916698}}, {"id": 2920074, "name": "Glasin", "country": "DE", "coord": {"lon": 11.73333, "lat": 53.916672}}, {"id": 2866029, "name": "Neudeck", "country": "DE", "coord": {"lon": 11.76667, "lat": 50.633331}}, {"id": 2894006, "name": "Kaisershagen", "country": "DE", "coord": {"lon": 10.48333, "lat": 51.26667}}, {"id": 6554832, "name": "Biebelnheim", "country": "DE", "coord": {"lon": 8.17056, "lat": 49.7967}}, {"id": 2949277, "name": "Biebelnheim", "country": "DE", "coord": {"lon": 8.17056, "lat": 49.796669}}, {"id": 2939040, "name": "Dangstetten", "country": "DE", "coord": {"lon": 8.33333, "lat": 47.599998}}, {"id": 2857133, "name": "Opsen", "country": "DE", "coord": {"lon": 7.66667, "lat": 50.783329}}, {"id": 6554187, "name": "Ailertchen", "country": "DE", "coord": {"lon": 7.93333, "lat": 50.599998}}, {"id": 2958846, "name": "Ailertchen", "country": "DE", "coord": {"lon": 7.93333, "lat": 50.599998}}, {"id": 2808528, "name": "Willitzgr\u00fcn", "country": "DE", "coord": {"lon": 12.24057, "lat": 50.40255}}, {"id": 2852721, "name": "P\u00f6nning", "country": "DE", "coord": {"lon": 12.48333, "lat": 48.833328}}, {"id": 6557043, "name": "Neuendorf", "country": "DE", "coord": {"lon": 9.65, "lat": 50.033298}}, {"id": 2865795, "name": "Neuendorf", "country": "DE", "coord": {"lon": 9.65, "lat": 50.033329}}, {"id": 6548126, "name": "Kramerhof", "country": "DE", "coord": {"lon": 13.05, "lat": 54.349998}}, {"id": 2884823, "name": "Kramerhof", "country": "DE", "coord": {"lon": 13.05412, "lat": 54.353661}}, {"id": 6552107, "name": "Kattendorf", "country": "DE", "coord": {"lon": 10.0167, "lat": 53.849998}}, {"id": 2892325, "name": "Kattendorf", "country": "DE", "coord": {"lon": 10.01667, "lat": 53.849998}}, {"id": 6551643, "name": "Bosau", "country": "DE", "coord": {"lon": 10.4302, "lat": 54.1054}}, {"id": 2945945, "name": "Bosau", "country": "DE", "coord": {"lon": 10.43333, "lat": 54.116669}}, {"id": 2940743, "name": "Busdorf", "country": "DE", "coord": {"lon": 10.08333, "lat": 54.099998}}, {"id": 6552539, "name": "Wietzen", "country": "DE", "coord": {"lon": 9.0734, "lat": 52.7103}}, {"id": 2809089, "name": "Wietzen", "country": "DE", "coord": {"lon": 9.08333, "lat": 52.716671}}, {"id": 2814554, "name": "Wallmering", "country": "DE", "coord": {"lon": 12.75, "lat": 49.200001}}, {"id": 2823605, "name": "Teisnach", "country": "DE", "coord": {"lon": 13, "lat": 49.033329}}, {"id": 6555967, "name": "Beimerstetten", "country": "DE", "coord": {"lon": 9.98333, "lat": 48.483299}}, {"id": 2951340, "name": "Beimerstetten", "country": "DE", "coord": {"lon": 9.98333, "lat": 48.48333}}, {"id": 6555471, "name": "W\u00e4schenbeuren", "country": "DE", "coord": {"lon": 9.68698, "lat": 48.759892}}, {"id": 2813847, "name": "Waschenbeuren", "country": "DE", "coord": {"lon": 9.68735, "lat": 48.759911}}, {"id": 2925150, "name": "Freienhufen", "country": "DE", "coord": {"lon": 13.96667, "lat": 51.583328}}, {"id": 2904127, "name": "Hinterheuweiler", "country": "DE", "coord": {"lon": 7.9, "lat": 48.049999}}, {"id": 6552353, "name": "Hahausen", "country": "DE", "coord": {"lon": 10.2167, "lat": 51.950001}}, {"id": 2912392, "name": "Hahausen", "country": "DE", "coord": {"lon": 10.21667, "lat": 51.950001}}, {"id": 6552517, "name": "Pegestorf", "country": "DE", "coord": {"lon": 9.5, "lat": 51.9333}}, {"id": 2855066, "name": "Pegestorf", "country": "DE", "coord": {"lon": 9.49682, "lat": 51.92775}}, {"id": 6548073, "name": "L\u00e4rz", "country": "DE", "coord": {"lon": 12.75, "lat": 53.299999}}, {"id": 2880404, "name": "Larz", "country": "DE", "coord": {"lon": 12.75, "lat": 53.299999}}, {"id": 2823842, "name": "Taubing", "country": "DE", "coord": {"lon": 13.66871, "lat": 48.586201}}, {"id": 6552813, "name": "Steinkirchen", "country": "DE", "coord": {"lon": 9.6025, "lat": 53.579102}}, {"id": 2827862, "name": "Steinkirchen", "country": "DE", "coord": {"lon": 9.61111, "lat": 53.56601}}, {"id": 2932163, "name": "Eichholz", "country": "DE", "coord": {"lon": 11.55, "lat": 50.066669}}, {"id": 6553292, "name": "Altenahr", "country": "DE", "coord": {"lon": 6.9917, "lat": 50.516899}}, {"id": 2957883, "name": "Altenahr", "country": "DE", "coord": {"lon": 6.99206, "lat": 50.516941}}, {"id": 2844651, "name": "Rossleben", "country": "DE", "coord": {"lon": 11.43333, "lat": 51.299999}}, {"id": 2953810, "name": "Baalberge", "country": "DE", "coord": {"lon": 11.8, "lat": 51.76667}}, {"id": 2958065, "name": "Altbensdorf", "country": "DE", "coord": {"lon": 12.33333, "lat": 52.416672}}, {"id": 2936631, "name": "Doberlug-Kirchhain", "country": "DE", "coord": {"lon": 13.56667, "lat": 51.616669}}, {"id": 2857862, "name": "Oestinghausen", "country": "DE", "coord": {"lon": 8.1, "lat": 51.633331}}, {"id": 2829595, "name": "Stammbach", "country": "DE", "coord": {"lon": 11.68333, "lat": 50.150002}}, {"id": 2821382, "name": "Treinreuth", "country": "DE", "coord": {"lon": 11.75, "lat": 49.73333}}, {"id": 2822564, "name": "Thungen", "country": "DE", "coord": {"lon": 9.85944, "lat": 49.942219}}, {"id": 2877201, "name": "Lindflur", "country": "DE", "coord": {"lon": 9.93056, "lat": 49.711941}}, {"id": 6557010, "name": "Buchbrunn", "country": "DE", "coord": {"lon": 10.1369, "lat": 49.75}}, {"id": 2942706, "name": "Buchbrunn", "country": "DE", "coord": {"lon": 10.13333, "lat": 49.76667}}, {"id": 6556464, "name": "Oberp\u00f6ring", "country": "DE", "coord": {"lon": 12.8333, "lat": 48.700001}}, {"id": 2859412, "name": "Oberporing", "country": "DE", "coord": {"lon": 12.83333, "lat": 48.700001}}, {"id": 6556227, "name": "Mammendorf", "country": "DE", "coord": {"lon": 11.1376, "lat": 48.217899}}, {"id": 2874006, "name": "Mammendorf", "country": "DE", "coord": {"lon": 11.15, "lat": 48.200001}}, {"id": 2864619, "name": "Neulehn", "country": "DE", "coord": {"lon": 12.53333, "lat": 50.533329}}, {"id": 2878294, "name": "Leutersbach", "country": "DE", "coord": {"lon": 12.51667, "lat": 50.599998}}, {"id": 6548735, "name": "Wachau", "country": "DE", "coord": {"lon": 13.9, "lat": 51.166698}}, {"id": 2815782, "name": "Wachau", "country": "DE", "coord": {"lon": 13.9, "lat": 51.166672}}, {"id": 2880865, "name": "Langenwolmsdorf", "country": "DE", "coord": {"lon": 14.11657, "lat": 51.042469}}, {"id": 2900844, "name": "Hohnstein", "country": "DE", "coord": {"lon": 14.11408, "lat": 50.979912}}, {"id": 2910141, "name": "Kurort Hartha", "country": "DE", "coord": {"lon": 13.55, "lat": 50.98333}}, {"id": 2839041, "name": "Schkortleben", "country": "DE", "coord": {"lon": 12.01667, "lat": 51.25}}, {"id": 2886300, "name": "K\u00f6llme", "country": "DE", "coord": {"lon": 11.81667, "lat": 51.5}}, {"id": 2949765, "name": "Betheln", "country": "DE", "coord": {"lon": 9.79397, "lat": 52.114311}}, {"id": 6552527, "name": "Hilgermissen", "country": "DE", "coord": {"lon": 9.15605, "lat": 52.8442}}, {"id": 2904748, "name": "Hilgermissen", "country": "DE", "coord": {"lon": 9.16667, "lat": 52.849998}}, {"id": 6555507, "name": "Sulzbach an der Murr", "country": "DE", "coord": {"lon": 9.5003, "lat": 49.003201}}, {"id": 2824804, "name": "Sulzbach an der Murr", "country": "DE", "coord": {"lon": 9.5003, "lat": 49.003029}}, {"id": 6555773, "name": "V\u00f6rstetten", "country": "DE", "coord": {"lon": 7.85, "lat": 48.0667}}, {"id": 2816010, "name": "Vorstetten", "country": "DE", "coord": {"lon": 7.85, "lat": 48.066669}}, {"id": 6555763, "name": "Wittnau", "country": "DE", "coord": {"lon": 7.81667, "lat": 47.950001}}, {"id": 2807215, "name": "Wittnau", "country": "DE", "coord": {"lon": 7.81667, "lat": 47.950001}}, {"id": 2820620, "name": "Ubbedissen", "country": "DE", "coord": {"lon": 8.63333, "lat": 51.98333}}, {"id": 6555996, "name": "Weidenstetten", "country": "DE", "coord": {"lon": 9.99674, "lat": 48.552521}}]